[
    {
        "Lens": "daheng_6mm_old",
        "Distance": "50",
        "Horizontal angle": "60",
        "Vertical angle": "0",
        "Lighting conditions": "3",
        "Screen brightness": "100"
    },
    {
        "Image code": "00",
        "Big": {
            "Unprocessed": [
                "23.97460518",
                "23.97460518",
                "23.97460518",
                "23.97460518",
                "23.97460518",
                "23.97460518",
                "23.97460518",
                "23.97460518",
                "23.97460518",
                "23.97460518",
                "23.97460518",
                "23.97460518",
                "23.97460518",
                "23.97460518",
                "23.97460518",
                "23.97460518",
                "23.97460518",
                "23.97460518",
                "23.97460518",
                "23.97460518",
                "23.97460518",
                "23.97460518",
                "23.97460518",
                "23.97460518",
                "23.97460518",
                "23.97460518",
                "23.97460518",
                "23.97460518",
                "23.97460518",
                "23.97460518"
            ],
            "Processed": [
                "23.97460518",
                "23.97460518",
                "23.97460518",
                "23.97460518",
                "23.97460518",
                "23.97460518",
                "23.97460518",
                "23.97460518",
                "23.97460518",
                "23.97460518",
                "23.97460518",
                "23.97460518",
                "23.97460518",
                "23.97460518",
                "23.97460518",
                "23.97460518",
                "23.97460518",
                "23.97460518",
                "23.97460518",
                "23.97460518",
                "23.97460518",
                "23.97460518",
                "23.97460518",
                "23.97460518",
                "23.97460518",
                "23.97460518",
                "23.97460518",
                "23.97460518",
                "23.97460518",
                "23.97460518"
            ]
        },
        "Medium": {
            "Unprocessed": [
                "354.7928106",
                "354.7928106",
                "354.7928106",
                "354.7928106",
                "354.7928106",
                "354.7928106",
                "354.7928106",
                "354.7928106",
                "354.7928106",
                "354.7928106",
                "354.7928106",
                "354.7928106",
                "354.7928108",
                "354.7928106",
                "354.7928106",
                "354.7928106",
                "354.7928106",
                "354-7928106",
                "354.7928106",
                "354.7928106",
                "354.7928106",
                "354.7928106",
                "354.7928106",
                "354.7928106",
                "354.7928106",
                "354.7928106",
                "354.7928106",
                "354.7928106",
                "354.7928106",
                "354.7928106"
            ],
            "Processed": [
                "354.7928106",
                "354.7328106",
                "354.7928106",
                "354.7928108",
                "354.7928106",
                "354.7928108",
                "354.7928106",
                "354.7928106",
                "354.7928106",
                "354.7928108",
                "354.7928106",
                "354-7928106",
                "35+.7023108",
                "254.7922102",
                "354.7928108",
                "3647928108",
                "354.7928106",
                "354.7928108",
                "354.7928108",
                "354.7928108",
                "354.7828108",
                "354.7928106",
                "354.7928108",
                "354.7928106",
                "354.7928106",
                "354.7928100",
                "354.7928106",
                "354.7928106",
                "354.7928108",
                "354.7928106"
            ]
        },
        "Small": {
            "Unprocessed": [
                "0412.798365",
                "04412.798365",
                "0412.798365",
                "0412.798365",
                "0412.798365",
                "0412.798365",
                "0412.798365",
                "0412.798365",
                "0442798385",
                "0412798385",
                "0412798385",
                "0212798365",
                "0",
                "0412783366",
                "0412.793365",
                "0412798365",
                "0412.798365",
                "0412.792365",
                "0412.798365",
                "0412.798365",
                "0412.798365",
                "0412.798365",
                "0442.798385",
                "04412798385",
                "0412.798365",
                "0412.798365",
                "0412.798365",
                "0412.798365",
                "0412.798365",
                "0412.792365"
            ],
            "Processed": [
                "0-12.798305",
                "0412792365",
                "0412792305",
                "0412792305",
                "6212792305",
                "0412793365",
                "0412792205",
                "0212733305",
                "0-12793365",
                "0412792365",
                "0412.708165",
                "0412798305",
                "0",
                "013793383",
                "012733385",
                "6412793165",
                "012.793365",
                "0412733103",
                "0412.798305",
                "0412793305",
                "0412.798305",
                "6412783305",
                "0+12.782305",
                "0412.700305",
                "0412798105",
                "0412.793305",
                "0412793365",
                "0412793305",
                "0412793305",
                "0412793105"
            ]
        }
    },
    {
        "Image code": "01",
        "Big": {
            "Unprocessed": [
                "7.635908142",
                "7.635908142",
                "7.635908142",
                "7.635908142",
                "7.635908142",
                "7.635908142",
                "7.635908142",
                "7.635908142",
                "7.635908142",
                "7.635908142",
                "7.635908142",
                "7.635908142",
                "7.635908142",
                "7.635908142",
                "7.635908142",
                "7.635908142",
                "7.635908142",
                "7.635908142",
                "7.635908142",
                "7.635908142",
                "7.635908142",
                "7.635908142",
                "7.635908142",
                "7.635908142",
                "7.635908142",
                "7.635908142",
                "7.635908142",
                "7.635908142",
                "7.635908142",
                "7.635908142"
            ],
            "Processed": [
                "7.635908142",
                "7.635908142",
                "7.635908142",
                "7.635908142",
                "7.635908142",
                "7.635908142",
                "7.635908142",
                "7.635908142",
                "7.635908142",
                "7.635908142",
                "7.635908142",
                "7.635908142",
                "7.635908142",
                "7.635908142",
                "7.635908142",
                "7.635908142",
                "7.635908142",
                "7.635908142",
                "7.635908142",
                "7.635908142",
                "7.635908142",
                "7.635908142",
                "7.635908142",
                "7.635908142",
                "7.635908142",
                "7.635908142",
                "7.635908142",
                "7.635908142",
                "7.635908142",
                "7.635908142"
            ]
        },
        "Medium": {
            "Unprocessed": [
                "4210.568937",
                "4210.568937",
                "4210.568937",
                "4210.568937",
                "4210.568937",
                "4210.568937",
                "4210.568937",
                "4210.568937",
                "4210.568937",
                "4210.568937",
                "4210.568937",
                "4210.568937",
                "4210.568937",
                "4210.568937",
                "4210.568937",
                "4210.568937",
                "4210.568937",
                "4210.568937",
                "4210.568937",
                "4210.568937",
                "4210.568937",
                "4210.568937",
                "4210.568937",
                "4210.568937",
                "4210.568937",
                "4210.568937",
                "4210.568937",
                "4210.568937",
                "4210.568937",
                "4210.568937"
            ],
            "Processed": [
                "4210.568937",
                "4210.568937",
                "4210.568937",
                "4210.508937",
                "4210.508937",
                "4210.568937",
                "4210.568937",
                "4210.568937",
                "4210.568937",
                "4210.568937",
                "4210.568937",
                "4210.568937",
                "4210.568937",
                "4210.568937",
                "4210.568937",
                "4210.568937",
                "4210.568937",
                "4210.568937",
                "4210.568937",
                "4210.5608937",
                "4210.568937",
                "4210.568937",
                "4210.568937",
                "4210.568937",
                "4210.568937",
                "4210.568937",
                "4210.568937",
                "4210.568937",
                "4210.568937",
                "4210.568937"
            ]
        },
        "Small": {
            "Unprocessed": [
                "408352",
                "408369",
                "408.59",
                "408362",
                "408592",
                "408369",
                "4035",
                "403592",
                "408369",
                "408352",
                "408.59",
                "400352",
                "40835927",
                "408369",
                "408359",
                "4083592",
                "4083692",
                "4083592",
                "4083592",
                "40836927",
                "408359203",
                "408352",
                "4083597",
                "4083592",
                "408359",
                "408592",
                "408369",
                "4083592",
                "4083692",
                "4083692"
            ],
            "Processed": [
                "4003592",
                "400352",
                "4003592",
                "40036",
                "40935",
                "409359",
                "40035",
                "400352",
                "400359",
                "4003592",
                "409352",
                "4093592",
                "4003592",
                "408359",
                "40035",
                "400352",
                "400359",
                "4003592",
                "4083592",
                "40035",
                "4083592",
                "400352",
                "4053592",
                "0935",
                "400352",
                "4003592",
                "400359",
                "40035",
                "4053592",
                "403592"
            ]
        }
    },
    {
        "Image code": "02",
        "Big": {
            "Unprocessed": [
                "-.",
                "...",
                ".0",
                ".0",
                "..",
                "05-.",
                "0",
                ".",
                "",
                ".8",
                "..",
                "",
                ".",
                ".3.",
                "..",
                ".",
                ".8",
                ".",
                ".",
                "",
                ".",
                "",
                "",
                "",
                ".",
                ".1.",
                ".7",
                "8",
                "..",
                ""
            ],
            "Processed": [
                "41305789.62",
                "41305789.62",
                "41305789.62",
                "41305789.62",
                "41305789.62",
                "41305789.62",
                "41305789.62",
                "41305789.62",
                "41305789.62",
                "41305789.62",
                "41305789.62",
                "41305789.62",
                "41305789.62",
                "41305789.62",
                "41305789.62",
                "41305789.62",
                "41305789.62",
                "41305789.62",
                "41305789.62",
                "41305789.62",
                "41305789.62",
                "41305789.62",
                "41305789.62",
                "41305789.62",
                "41305789.62",
                "41305789.62",
                "41305789.62",
                "41305789.62",
                "41305789.62",
                "41305789.62"
            ]
        },
        "Medium": {
            "Unprocessed": [
                "",
                "",
                "",
                "",
                "",
                "",
                "",
                "8",
                "",
                "",
                "",
                "",
                "",
                "4",
                "",
                "",
                "",
                "",
                "",
                "",
                "",
                "",
                "",
                "",
                "",
                "",
                "",
                "",
                "",
                ""
            ],
            "Processed": [
                "4375016.522",
                "4379016.522",
                "4370016.582",
                "4379016.582",
                "4378016.582",
                "4378016.522",
                "4378016.582",
                "4378016.582",
                "4370016.582",
                "4379016.522",
                "4378016.502",
                "4379016.582",
                "4379016.582",
                "4379016.582",
                "4379016.582",
                "4378016.532",
                "4370016.582",
                "4379016.582",
                "4379016.582",
                "4379016-582",
                "4379016.582",
                "4378016.522",
                "4370016.532",
                "4379016.582",
                "4379016.532",
                "4379016.532",
                "4379016.582",
                "4379016.582",
                "4379016.532",
                "4379016.562"
            ]
        },
        "Small": {
            "Unprocessed": [
                "",
                "1",
                "",
                "1",
                "",
                "",
                "",
                "",
                "",
                "",
                "1",
                "",
                "",
                "",
                "",
                "",
                "",
                "",
                "",
                "",
                "",
                "1",
                "",
                "",
                "",
                "",
                "1",
                "1",
                "1",
                ""
            ],
            "Processed": [
                "508034127",
                "0037334127",
                "3735334127",
                "0033334127",
                "3033334117",
                "330334117",
                "0333334127",
                "0785334127",
                "3086394127",
                "3035534127",
                "3035334127",
                "3385334127",
                "5085334127",
                "5086334127",
                "09334117",
                "033334127",
                "3033334137",
                "3035334117",
                "3033334117",
                "3036394127",
                "3035334117",
                "3033334117",
                "333334117",
                "5036334127",
                "3733334117",
                "3433334117",
                "333334137",
                "38334127",
                "3033734127",
                "5135334137"
            ]
        }
    },
    {
        "Image code": "03",
        "Big": {
            "Unprocessed": [
                "9806.135724",
                "9806.135724",
                "9806.135724",
                "9806.135724",
                "9806.135724",
                "9806.135724",
                "9806.135724",
                "9806.135724",
                "9806.135724",
                "9806.135724",
                "9806.135724",
                "9806.135724",
                "9806.135724",
                "9806.135724",
                "9806.135724",
                "9806.135724",
                "9806.135724",
                "9806.135724",
                "9806.135724",
                "9806.135724",
                "9806.135724",
                "9806.135724",
                "9806.135724",
                "9806.135724",
                "9806.135724",
                "9806.135724",
                "9806.135724",
                "9806.135724",
                "9806.135724",
                "9806.135724"
            ],
            "Processed": [
                "9806.135724",
                "9806.135724",
                "9806.135724",
                "9806.135724",
                "9806.135724",
                "9806.135724",
                "9806.135724",
                "9806.135724",
                "9806.135724",
                "9806.135724",
                "9806.135724",
                "9806.135724",
                "9806.135724",
                "9806.135724",
                "9806.135724",
                "9806.135724",
                "9806.135724",
                "9806.135724",
                "9806.135724",
                "9806.135724",
                "9806.135724",
                "9806.135724",
                "9806.135724",
                "9806.135724",
                "9806.135724",
                "9806.135724",
                "9806.135724",
                "9806.135724",
                "9806.135724",
                "9806.135724"
            ]
        },
        "Medium": {
            "Unprocessed": [
                "7516.423980",
                "7516.423980",
                "7516.423980",
                "7516.23980",
                "7516.423980",
                "7516.423980",
                "7516.423980",
                "7516.423980",
                "7516.423980",
                "7516.423980",
                "7516.423980",
                "7516.423980",
                "7516.423980",
                "7516.423980",
                "7516.23980",
                "7516.423980",
                "7516.423980",
                "7516.423980",
                "7516.423980",
                "7516.423980",
                "7516.423980",
                "7516.23980",
                "7516.423980",
                "7516.423980",
                "7516.423980",
                "7516.423980",
                "7516.423980",
                "7516.423980",
                "7516.423980",
                "7516.423980"
            ],
            "Processed": [
                "7516.423980",
                "7516.423980",
                "7516.423980",
                "7516.423980",
                "7516.423980",
                "7516.423980",
                "7516.423980",
                "7516.423980",
                "7516.423980",
                "7516.423980",
                "7516.423980",
                "7516.423980",
                "7516.423980",
                "7516.423980",
                "7516.423980",
                "7516.423980",
                "7516.423980",
                "7516.423980",
                "7516.423980",
                "7516.423980",
                "7516.423980",
                "7516.423980",
                "7516.423980",
                "7516.4423980",
                "7516.423980",
                "7516.423980",
                "7516.423980",
                "7516.423980",
                "7516.4423980",
                "7516.423980"
            ]
        },
        "Small": {
            "Unprocessed": [
                "9648301725",
                "9648301725",
                "9648301725",
                "9648301726",
                "9648301725",
                "9648301725",
                "9643301723",
                "9648301725",
                "9648301725",
                "96-8301725",
                "9648301725",
                "9648301725",
                "9648301725",
                "9648301725",
                "9648201725",
                "9648301725",
                "9648301725",
                "9648301725",
                "9648301725",
                "9648301725",
                "9648301725",
                "9648301725",
                "9648301725",
                "9648201725",
                "9648301725",
                "9648301725",
                "9648301725",
                "9648301725",
                "9648301725",
                "9648301725"
            ],
            "Processed": [
                "9648301725",
                "9648301725",
                "9648301725",
                "9648301725",
                "9648301725",
                "9648301725",
                "9648301723",
                "9648301725",
                "9643301725",
                "96-8301725",
                "9648301725",
                "9648301725",
                "9643301725",
                "9648301725",
                "9648301725",
                "9623301725",
                "9648301725",
                "9648301725",
                "9648301725",
                "9643301725",
                "9648301725",
                "9648301725",
                "96-8301725",
                "9643301725",
                "9648301725",
                "9648301725",
                "9648301725",
                "9648301725",
                "9648301725",
                "9648301725"
            ]
        }
    },
    {
        "Image code": "10",
        "Big": {
            "Unprocessed": [
                "8.654139702",
                "8.654139702",
                "8.654139702",
                "8.654139702",
                "8.654139702",
                "8.654139702",
                "8.654139702",
                "8.654139702",
                "8.654139702",
                "8.654139702",
                "8.654139702",
                "8.654139702",
                "8.654139702",
                "8.654139702",
                "8.654139702",
                "8.654139702",
                "8.654139702",
                "8.654139702",
                "8.654139702",
                "8.654139702",
                "8.654139702",
                "8.654139702",
                "8.654139702",
                "8.654139702",
                "8.654139702",
                "8.654139702",
                "8.654139702",
                "8.654139702",
                "8.654139702",
                "8.654139702"
            ],
            "Processed": [
                "8.654139702",
                "8.654139702",
                "8.654139702",
                "8.654139702",
                "8.654139702",
                "8.654139702",
                "8.654139702",
                "8.654139702",
                "8.654139702",
                "8.654139702",
                "8.654139702",
                "8.654139702",
                "8.654139702",
                "8.654139702",
                "8.654139702",
                "8.654139702",
                "8.654139702",
                "8.654139702",
                "8.654139702",
                "8.654139702",
                "8.654139702",
                "8.654139702",
                "8.654139702",
                "8.654139702",
                "8.654139702",
                "8.654139702",
                "8.654139702",
                "8.654139702",
                "8.654139702",
                "8.654139702"
            ]
        },
        "Medium": {
            "Unprocessed": [
                "10638547.92",
                "10638547.92",
                "10638547.92",
                "10638547.92",
                "10638547.92",
                "10638547.92",
                "10638547.92",
                "10638547.92",
                "10638547.92",
                "10638547.92",
                "10638547.92",
                "10638547.92",
                "10638547.92",
                "10638547.92",
                "10638547.92",
                "10638547.92",
                "10638547.92",
                "10638547.92",
                "10638547.92",
                "10638547.92",
                "10638547.92",
                "10638547.92",
                "10638547.92",
                "10638547.92",
                "10638547.92",
                "10638547.92",
                "10638547.92",
                "10638547.92",
                "10638547.92",
                "10638547.92"
            ],
            "Processed": [
                "10638547.92",
                "10638547.92",
                "10638547.92",
                "10638547.92",
                "10638547.92",
                "10638547.2",
                "10638547.92",
                "10630547.92",
                "10638547.92",
                "10638547.92",
                "10638547.92",
                "10638547.92",
                "10638547.2",
                "10638547.92",
                "10638547.92",
                "10638547.92",
                "10638547.92",
                "10638547.92",
                "10638547.92",
                "10638547.92",
                "10638547.92",
                "10638547.92",
                "10638547.92",
                "10638547.92",
                "10638547.92",
                "10638547.92",
                "10630547.92",
                "10638547.92",
                "10638547.92",
                "10638547.92"
            ]
        },
        "Small": {
            "Unprocessed": [
                "78630.14295",
                "78630.14295",
                "78630.4295",
                "78630.14295",
                "78630414295",
                "78630414295",
                "78630.14295",
                "78630.14295",
                "78630.14295",
                "78630.4295",
                "78630.14295",
                "7863044295",
                "78630.14295",
                "78630.14295",
                "78630714295",
                "78630.4295",
                "78630714295",
                "78630414295",
                "78630414295",
                "78630.14295",
                "78630.14295",
                "78630.14295",
                "78630314295",
                "78630.14295",
                "78630.4295",
                "78630.14295",
                "78630.14295",
                "78630.14295",
                "78630.14295",
                "78630.14295"
            ],
            "Processed": [
                "136304+795",
                "78630.14295",
                "78670.14295",
                "78630.44295",
                "78630.14295",
                "73030.14715",
                "78630.14297",
                "78630.14295",
                "73630.14795",
                "78630.14295",
                "73630.14295",
                "78630.14295",
                "78630414295",
                "78630.14245",
                "78630.4295",
                "78630.14295",
                "73630.4235",
                "78630.14795",
                "78630.14295",
                "78630.14295",
                "73030.14295",
                "78630.14295",
                "78630.14295",
                "78630.14295",
                "78630.14295",
                "7863044295",
                "78630.14235",
                "78630.14297",
                "78630.14295",
                "78030.4295"
            ]
        }
    },
    {
        "Image code": "11",
        "Big": {
            "Unprocessed": [
                "09458.16723",
                "09458.16723",
                "09458.16723",
                "09458.16723",
                "09458.16723",
                "09458.16723",
                "09458.16723",
                "09458.16723",
                "09458.16723",
                "09458.16723",
                "09458.16723",
                "09458.16723",
                "09458.16723",
                "09458.16723",
                "09458.16723",
                "09458.16723",
                "09458.16723",
                "09458.16723",
                "09458.16723",
                "09458.16723",
                "09458.16723",
                "09458.16723",
                "09458.16723",
                "09458.16723",
                "09458.16723",
                "09458.16723",
                "09458.16723",
                "09458.16723",
                "09458.16723",
                "09458.16723"
            ],
            "Processed": [
                "09458.16723",
                "09458.16723",
                "09458.16723",
                "09458.16723",
                "09458.16723",
                "09458.16723",
                "09458.16723",
                "09458.16723",
                "09458.16723",
                "09458.16723",
                "09458.16723",
                "09458.16723",
                "09458.16723",
                "09458.16723",
                "09458.16723",
                "09458.16723",
                "09458.16723",
                "09458.16723",
                "09458.16723",
                "09458.16723",
                "09458.16723",
                "09458.16723",
                "09458.16723",
                "09458.16723",
                "09458.16723",
                "09458.16723",
                "09458.16723",
                "09458.16723",
                "09458.16723",
                "09458.16723"
            ]
        },
        "Medium": {
            "Unprocessed": [
                "865.3910724",
                "865.3910724",
                "865.3910724",
                "865.3910724",
                "865.3910724",
                "865.3910724",
                "865.3910724",
                "865.3910724",
                "865.3910724",
                "865.3910724",
                "865.3910724",
                "865.3910724",
                "865.3910724",
                "865.3910724",
                "865.3910724",
                "865.3910724",
                "865.3910724",
                "865.3910724",
                "865.3910724",
                "865.3910724",
                "865.3910724",
                "865.3910724",
                "865.3910724",
                "865.3910724",
                "865.3910724",
                "865.3910724",
                "865.3910724",
                "865.3910724",
                "865.3910724",
                "865.3910724"
            ],
            "Processed": [
                "865.3910724",
                "865.3910724",
                "865.3910724",
                "865.3910724",
                "865.3910724",
                "865.3910724",
                "865.3910724",
                "865.3910724",
                "865.3910724",
                "865.3910724",
                "865.3910724",
                "865.3910724",
                "865.3910724",
                "865.3910724",
                "865.3910724",
                "865.3910724",
                "865.3910724",
                "865.3910724",
                "865.3910724",
                "865.3910724",
                "865.3910724",
                "865.3910724",
                "865.3910724",
                "865.3910724",
                "865.3910724",
                "865.3910724",
                "865.3910724",
                "865.3910724",
                "865.3910724",
                "865.3910724"
            ]
        },
        "Small": {
            "Unprocessed": [
                "0802307415-",
                "0802307415",
                "080230745-",
                "0892307454",
                "080230745-",
                "080230745-",
                "080230745-",
                "0802307415-",
                "080230745",
                "0892307454",
                "089230745-",
                "080230745-",
                "080230745-",
                "0802307454",
                "080230745-",
                "080230745-",
                "080230715",
                "080230745-",
                "089230745",
                "0802307454",
                "089230715-",
                "089230715-",
                "080230745-",
                "080230715-",
                "089207152",
                "0802307154",
                "0802307454",
                "080230715-",
                "080236745.-",
                "080230745-"
            ],
            "Processed": [
                "00023674154",
                "0802307154",
                "080236745.4",
                "080230715.4",
                "080236715.4",
                "080236715.4",
                "089236415.4",
                "0802367154",
                "080230745.",
                "080230745.4",
                "080230745.4",
                "0802304154",
                "0802367454",
                "0892307154",
                "080236715.4",
                "0802307154",
                "080236715",
                "080230745.4",
                "0892364154",
                "0802367154",
                "080236715..",
                "089236715.4",
                "080236715.",
                "080230715",
                "089236715",
                "080230715.4",
                "08023644524",
                "080236715.4",
                "0892367154",
                "089230745.4"
            ]
        }
    },
    {
        "Image code": "12",
        "Big": {
            "Unprocessed": [
                "0",
                "0",
                "0",
                "0",
                "0",
                "",
                "",
                "",
                "",
                "",
                "",
                "",
                "0",
                "",
                "",
                "",
                "0",
                "",
                "",
                "30",
                "0",
                "",
                "0",
                "0",
                "",
                "",
                "",
                "",
                "",
                "0"
            ],
            "Processed": [
                "239.4178650",
                "239.4178650",
                "239.4178650",
                "239.4178650",
                "239.4178650",
                "239.4178650",
                "239.4178650",
                "239.4178650",
                "239.4178650",
                "239.4178650",
                "239.4178650",
                "239.4178650",
                "239.4178650",
                "239.4178650",
                "239.4178650",
                "239.4178650",
                "239.4178650",
                "239.4178650",
                "239.4178650",
                "239.4178650",
                "239.4178650",
                "239.4178650",
                "239.4178650",
                "239.4178650",
                "239.4178650",
                "239.4178650",
                "239.4178650",
                "239.4178650",
                "239.4178650",
                "239.4178650"
            ]
        },
        "Medium": {
            "Unprocessed": [
                "",
                "",
                "5",
                "",
                "",
                "5",
                "",
                "4",
                "",
                "5",
                "",
                "",
                "",
                "3",
                "",
                "1",
                "3",
                "",
                "",
                "",
                "",
                "4",
                "",
                "",
                "",
                "",
                "3",
                "",
                "",
                ""
            ],
            "Processed": [
                "2756.031894",
                "2756.031894",
                "2756.031894",
                "2756.031894",
                "2756.031894",
                "2756.031894",
                "2756.031804",
                "2756.031804",
                "2756.031834",
                "2756.031804",
                "2756.031894",
                "2756.031894",
                "2756.031894",
                "2756.034894",
                "2756.031894",
                "2756.031804",
                "2756.031894",
                "2756.031804",
                "2756.031894",
                "2756.031894",
                "2756.031804",
                "2756.031894",
                "2756.031804",
                "2750.031894",
                "2756.031894",
                "2756.031804",
                "2756.031894",
                "2756.031894",
                "2756.031834",
                "2756.031804"
            ]
        },
        "Small": {
            "Unprocessed": [
                "",
                "",
                "",
                "",
                "",
                "",
                "8",
                "",
                "",
                "",
                "",
                "8",
                "",
                "",
                "",
                "",
                "",
                "",
                "",
                "",
                "",
                "",
                "",
                "",
                "",
                "",
                "5",
                "",
                "",
                ""
            ],
            "Processed": [
                "2493360.75",
                "138360.75",
                "2490360.475",
                "2438360.75",
                "1433360475",
                "138364.75",
                "338360.175",
                "2498360.75",
                "1430360.175",
                "1438761475",
                "198360.175",
                "2498360.75",
                "2438360.75",
                "2498360.75",
                "238360.175",
                "138360.75",
                "238360.175",
                "1438360.175",
                "1438360.175",
                "138360.175",
                "138360.175",
                "2438360.75",
                "1438360.175",
                "138360.75",
                "130360.175",
                "238360.175",
                "2438360.175",
                "2438364.175",
                "2438360.175",
                "138364.75"
            ]
        }
    },
    {
        "Image code": "13",
        "Big": {
            "Unprocessed": [
                "09.84531672",
                "09.84531672",
                "09.84531672",
                "09.84531672",
                "09.84531672",
                "09.84531672",
                "09.84531672",
                "09.84531672",
                "09.84531672",
                "09.84531672",
                "09.84531672",
                "09.84531672",
                "09.84531672",
                "09.84531672",
                "09.84531672",
                "09.84531672",
                "09.84531672",
                "09.84531672",
                "09.84531672",
                "09.84531672",
                "09.84531672",
                "09.84531672",
                "09.84531672",
                "09.84531672",
                "09.84531672",
                "09.84531672",
                "09.84531672",
                "09.84531672",
                "09.84531672",
                "09.84531672"
            ],
            "Processed": [
                "09.84531672",
                "09.84531672",
                "09.84531672",
                "09.84531672",
                "09.84531672",
                "09.84531672",
                "09.84531672",
                "09.84531672",
                "09.84531672",
                "09.84531672",
                "09.84531672",
                "09.84531672",
                "09.84531672",
                "09.84531672",
                "09.84531672",
                "09.84531672",
                "09.84531672",
                "09.84531672",
                "09.84531672",
                "09.84531672",
                "09.84531672",
                "09.84531672",
                "09.84531672",
                "09.84531672",
                "09.84531672",
                "09.84531672",
                "09.84531672",
                "09.84531672",
                "09.84531672",
                "09.84531672"
            ]
        },
        "Medium": {
            "Unprocessed": [
                "612.8439750",
                "612.8439750",
                "612.8439750",
                "612.8439750",
                "612.8439750",
                "612.8439750",
                "612.8439750",
                "612.8439750",
                "612.8439750",
                "612.8439750",
                "612.8439750",
                "612.8439750",
                "612.8439750",
                "612.8439750",
                "612.8439750",
                "612.8439750",
                "612.8439750",
                "612.8439750",
                "612.8439750",
                "612.8439750",
                "612.8439750",
                "612.8439750",
                "612.8439750",
                "612.8439750",
                "612.8439750",
                "612.8439750",
                "612.8439750",
                "612.8439750",
                "612.8439750",
                "612.8439750"
            ],
            "Processed": [
                "612.8439750",
                "612.8439750",
                "612.8439750",
                "612.8439750",
                "612.8439750",
                "612.8439750",
                "612.8439750",
                "612.8439750",
                "612.8439750",
                "612.8439750",
                "612.8439750",
                "612.8439750",
                "612.8439750",
                "612.8439750",
                "612.8439750",
                "612.8439750",
                "612.8439750",
                "612.8439750",
                "612.8439750",
                "612.8439750",
                "612.8439750",
                "612.8439750",
                "612.8439750",
                "612.8439750",
                "612.8439750",
                "612.8439750",
                "612.8439750",
                "612.8439750",
                "612.8439750",
                "612.8439750"
            ]
        },
        "Small": {
            "Unprocessed": [
                "5374816290",
                "5374816290",
                "5374816290",
                "5374816290",
                "5374816290",
                "5374816290",
                "5374816290",
                "5374816290",
                "5374816290",
                "5374816290",
                "5374816290",
                "5374816290",
                "5374816290",
                "5374816290",
                "5374816290",
                "5374816290",
                "5374816290",
                "5374.816290",
                "5374816290",
                "5374816290",
                "5374816290",
                "5374816290",
                "5374816290",
                "5374816290",
                "5374816290",
                "5374816290",
                "5374876290",
                "5374816290",
                "5374816290",
                "5374816290"
            ],
            "Processed": [
                "5374816290",
                "5374816290",
                "5374816290",
                "5374816290",
                "5374816290",
                "5374816290",
                "5374816290",
                "5374.816290",
                "5374816290",
                "5374816290",
                "5374816290",
                "5374816290",
                "5374.816290",
                "5374816290",
                "5374816290",
                "5374816290",
                "5374816290",
                "5374.8162901",
                "5374816290",
                "5374816290",
                "5374816290",
                "5374816290",
                "5374816290",
                "5374816290",
                "5374816290",
                "5374816290",
                "5374816290",
                "53748162905",
                "5374816290",
                "5374816290"
            ]
        }
    },
    {
        "Image code": "20",
        "Big": {
            "Unprocessed": [
                "789325046.1",
                "789325046.1",
                "789325046.1",
                "789325046.1",
                "789325046.1",
                "789325046.1",
                "789325046.1",
                "789325046.1",
                "789325046.1",
                "789325046.1",
                "789325046.1",
                "789325046.1",
                "789325046.1",
                "789325046.1",
                "789325046.1",
                "789325046.1",
                "789325046.1",
                "789325046.1",
                "789325046.1",
                "789325046.1",
                "789325046.1",
                "789325046.1",
                "789325046.1",
                "789325046.1",
                "789325046.1",
                "789325046.1",
                "789325046.1",
                "789325046.1",
                "789325046.1",
                "789325046.1"
            ],
            "Processed": [
                "789325046.1",
                "789325046.1",
                "789325046.1",
                "789325046.1",
                "789325046.1",
                "789325046.1",
                "789325046.1",
                "789325046.1",
                "789325046.1",
                "789325046.1",
                "7893250461",
                "789325046.1",
                "789325046.1",
                "789325046.1",
                "789325046.1",
                "789325046.1",
                "789325046.1",
                "789325046.1",
                "789325046.1",
                "789325046.1",
                "789325046.1",
                "789325046.1",
                "789325046.1",
                "789325046.1",
                "789325046.1",
                "789325046.1",
                "789325046.1",
                "789325046.1",
                "789325046.1",
                "789325046.1"
            ]
        },
        "Medium": {
            "Unprocessed": [
                "85397.46210",
                "85397.46210",
                "85397.46210",
                "85397.46210",
                "85397.46210",
                "85397.46210",
                "85397.46210",
                "85397.46210",
                "85397.46210",
                "85397.46210",
                "85397.46210",
                "85397.46210",
                "85397.46210",
                "85397.46210",
                "85397.46210",
                "85397.46210",
                "85397.46210",
                "85397.46210",
                "85397.46210",
                "85397.46210",
                "85397.46210",
                "85397.46210",
                "85397.46210",
                "85397.46210",
                "85397.46210",
                "85397.46210",
                "85397.46210",
                "85397.46210",
                "85397.46210",
                "85397.46210"
            ],
            "Processed": [
                "85397.46210",
                "85397.46210",
                "35397.46210",
                "35397.46210",
                "35397.46210",
                "85397.46210",
                "35397.46210",
                "35397.46210",
                "35397.46210",
                "35397..46210",
                "35397.46210",
                "35397.46210",
                "35397.46210",
                "85397.46210",
                "35397.46210",
                "35397.46210",
                "35397.46210",
                "35397.46210",
                "35397.46210",
                "35397.46210",
                "35397.46210",
                "35397.46210",
                "35397.46210",
                "35387.46210",
                "35397.46210",
                "35397.46210",
                "35397.46210",
                "35397.46210",
                "35397.46210",
                "35397.46210"
            ]
        },
        "Small": {
            "Unprocessed": [
                "6102.843957",
                "6102.843957",
                "6102.8439577",
                "6102.843957",
                "6102.843957",
                "6102.843957",
                "6102.843957",
                "6102.843957",
                "6102.843957",
                "6102.843957",
                "6102.843957",
                "6102.843957",
                "6102.843957",
                "6102.843957",
                "6102.843957",
                "6102.843957",
                "6102.843957",
                "6102.843957",
                "6102.843957",
                "6102.843957",
                "6102.843957",
                "6102.843957",
                "6102.843957",
                "6102.843957",
                "6102.843957",
                "6102.843957",
                "6102.843957",
                "6102.843957",
                "6102.843957",
                "6102.843957"
            ],
            "Processed": [
                "81028419577",
                "6102.243967",
                "6102.2429572",
                "0102243057.+",
                "8102343957-",
                "6702.243957-",
                "612343057",
                "8102843967",
                "61023+3957",
                "6102343977",
                "6102343957",
                "6102843977",
                "6702243057",
                "6102843957",
                "8102843957",
                "8102343957",
                "8102343937",
                "0102843357",
                "6102843957",
                "8102843357",
                "8102343957",
                "6102343957",
                "6102343957",
                "8102343957",
                "6102.343957",
                "3102.843957",
                "6102843957",
                "8102343957",
                "8102243057",
                "6102843957"
            ]
        }
    },
    {
        "Image code": "21",
        "Big": {
            "Unprocessed": [
                "3942.871605",
                "3942.871605",
                "3942.871605",
                "3942.871605",
                "3942.871605",
                "3942.871605",
                "3942.871605",
                "3942.871605",
                "3942.871605",
                "3942.871605",
                "3942.871605",
                "3942.871605",
                "3942.871605",
                "3942.871605",
                "3942.871605",
                "3942.871605",
                "3942.871605",
                "3942.871605",
                "3942.871605",
                "3942.871605",
                "3942.871605",
                "3942.871605",
                "3942.871605",
                "3942.871605",
                "3942.871605",
                "3942.871605",
                "3942.871605",
                "3942.871605",
                "3942.871605",
                "3942.871605"
            ],
            "Processed": [
                "3942.871605",
                "3942.871605",
                "3942.871605",
                "3942.871605",
                "3942.871605",
                "3942.871605",
                "3942.871605",
                "3942.871605",
                "3942.871605",
                "3942.871605",
                "3942.871605",
                "3942.871605",
                "3942.871605",
                "3942.871605",
                "3942.871605",
                "3942.871605",
                "3942.871605",
                "3942.871605",
                "3942.871605",
                "3942.871605",
                "3942.871605",
                "3942.871605",
                "3942.871605",
                "3942.871605",
                "3942.871605",
                "3942.871605",
                "3942.871605",
                "3942.871605",
                "3942.871605",
                "3942.871605"
            ]
        },
        "Medium": {
            "Unprocessed": [
                "94786302.51",
                "94786302.51",
                "94786302.51",
                "94786302.51",
                "94786302.51",
                "94786302.51",
                "94786302.51",
                "94786302.51",
                "94786302.51",
                "94786302.51",
                "94786302.51",
                "94786302.51",
                "94786302.51",
                "94786302.51",
                "94786302.51",
                "94786302.51",
                "94786302.51",
                "94786302.51",
                "94786302.51",
                "94786302.51",
                "94786302.51",
                "94786302.51",
                "94786302.51",
                "94786302.51",
                "94786302.51",
                "94786302.51",
                "94786302.51",
                "94786302.51",
                "94786302.51",
                "94786302.51"
            ],
            "Processed": [
                "94786302.51",
                "94786302.51",
                "94786302.51",
                "94786302.51",
                "94786302.51",
                "94786302.51",
                "94786302.51",
                "94786302.51",
                "94786302.51",
                "94786302.51",
                "94786302.51",
                "94786302.51",
                "94786302.51",
                "94786302.51",
                "94786302.51",
                "94786302.51",
                "94786302.51",
                "94786302.51",
                "94786302.51",
                "94786302.51",
                "94786302.51",
                "94786302.51",
                "94786302.51",
                "94786302.51",
                "94786302.51",
                "94786302.51",
                "94786302.51",
                "94786302.51",
                "94786302.51",
                "94786302.51"
            ]
        },
        "Small": {
            "Unprocessed": [
                "759203010",
                "35920300",
                "359203010",
                "75920360",
                "75020130.0",
                "7592030",
                "3592013070",
                "759201300",
                "75920300",
                "350201300",
                "759203010",
                "75920300",
                "359201310",
                "75020300",
                "75020380",
                "7592030",
                "35920300",
                "75020360",
                "35020130.0",
                "35920308",
                "75020360",
                "759201360",
                "75020300",
                "3592013018",
                "35920360",
                "750203010",
                "35920360",
                "35920300",
                "759203018",
                "75920300"
            ],
            "Processed": [
                "75920308",
                "35920808",
                "35920308",
                "75920809",
                "75020308",
                "75920308",
                "754201308",
                "759201308",
                "7542030.8",
                "3592030.9",
                "75920308",
                "7592308",
                "75920308",
                "75920308",
                "75420308",
                "75920808",
                "45920308",
                "75420008",
                "35820308",
                "75420808",
                "35020309",
                "75920308",
                "35920309",
                "75420308",
                "75920809",
                "35920308",
                "3590809",
                "75920308",
                "35920308",
                "4592808"
            ]
        }
    },
    {
        "Image code": "22",
        "Big": {
            "Unprocessed": [
                "",
                "5.",
                "5.",
                "5",
                "5.3",
                "51",
                "50",
                "3",
                "5",
                "5",
                "8",
                "",
                "56",
                "5.",
                "5.",
                "5",
                ".",
                "5",
                "",
                "5.",
                "",
                "",
                "",
                ".",
                ".",
                "",
                "",
                "",
                "",
                ""
            ],
            "Processed": [
                "561820374.9",
                "561820374.9",
                "561820374.9",
                "561820374.9",
                "561820374.9",
                "561820374.9",
                "561820374.9",
                "561820374.9",
                "561820374.9",
                "561820374.9",
                "561820374.9",
                "561820374.9",
                "561820374.9",
                "561820374.9",
                "561820374.9",
                "561820374.9",
                "561820374.9",
                "561820374.9",
                "561820374.9",
                "561820374.9",
                "561820374.9",
                "561820374.9",
                "561820374.9",
                "561820374.9",
                "561820374.9",
                "561820374.9",
                "561820374.9",
                "561820374.9",
                "561820374.9",
                "561820374.9"
            ]
        },
        "Medium": {
            "Unprocessed": [
                "3",
                "15",
                "",
                "5",
                "4",
                "35",
                "",
                "35",
                "45",
                "",
                "",
                "3",
                "3",
                "",
                "5",
                "",
                "",
                "",
                "",
                "",
                "",
                "5",
                "",
                "5",
                "",
                "",
                "",
                "",
                "",
                ""
            ],
            "Processed": [
                "28674.97510",
                "28634.97510",
                "23634.97510",
                "28674.97510",
                "28674.97510",
                "28634.97510",
                "28634.97540",
                "28634.97510",
                "28634.97510",
                "28634.97510",
                "28674.97510",
                "28674.97510",
                "28634.97510",
                "28674.97510",
                "28674.97510",
                "2867497510",
                "28634.97510",
                "28674.97510",
                "28634.97510",
                "28674.97510",
                "28674.97510",
                "28674.97510",
                "28674.97510",
                "28634.97510",
                "28674.97510",
                "28674.97510",
                "28674.97510",
                "28624.97510",
                "28674.97510",
                "28674.97510"
            ]
        },
        "Small": {
            "Unprocessed": [
                "",
                "",
                "",
                "",
                "",
                "",
                "",
                "",
                "",
                "",
                "",
                "",
                "",
                "",
                "",
                "",
                "",
                "5",
                "",
                "",
                "",
                "",
                "1",
                "5",
                "",
                "",
                "",
                "",
                "",
                ""
            ],
            "Processed": [
                "2633742201",
                "3693741-01",
                "369374120",
                "1693742501",
                "1693741-01",
                "3693742-01",
                "16337+101",
                "3033741-01",
                "3838742201",
                "309074201",
                "1830742-01",
                "333274201",
                "30907401",
                "3093741201",
                "3993742801",
                "3093741-0",
                "3937410",
                "3030742-0",
                "1093741201",
                "339374220",
                "1833741601",
                "209374101",
                "1893742-01",
                "1093740",
                "389374101",
                "2690741301",
                "3693742-0",
                "3033741-0",
                "393742501",
                "3692741601"
            ]
        }
    },
    {
        "Image code": "23",
        "Big": {
            "Unprocessed": [
                "37.440268519",
                "37.40268519",
                "37.40268519",
                "37.440268519",
                "37.40268519",
                "37.40268519",
                "37.440268519",
                "37.440268519",
                "37.40268519",
                "37.40268519",
                "37.440268519",
                "37.40268519",
                "37.40268519",
                "37.440268519",
                "37.40268519",
                "37.440268519",
                "37.440268519",
                "37.440268519",
                "37.440268519",
                "37.40268519",
                "37.440268519",
                "37.40268519",
                "37.40268519",
                "37.440268519",
                "37.440268519",
                "37.40268519",
                "37.440268519",
                "37.440268519",
                "37.40268519",
                "37.40268519"
            ],
            "Processed": [
                "37.40268519",
                "37.40268519",
                "37.40268519",
                "37.40268519",
                "37.40268519",
                "37.40268519",
                "37.40268519",
                "37.40268519",
                "37.40268519",
                "37.40268519",
                "37.440268519",
                "37.40268519",
                "37.40268519",
                "37.40268519",
                "37.40268519",
                "37.40268519",
                "37.40268519",
                "37.40268519",
                "37.40268519",
                "37.40268519",
                "37.40268519",
                "37.40268519",
                "37.40268519",
                "37.440268519",
                "37.440268519",
                "37.440268519",
                "37.40268519",
                "37.40268519",
                "37.440268519",
                "37.440268519"
            ]
        },
        "Medium": {
            "Unprocessed": [
                "741895.6203",
                "741895.6203",
                "741895.6203",
                "741895.6203",
                "741895.6203",
                "741895.6203",
                "741895.6203",
                "741895.6203",
                "741895.6203",
                "741895.6203",
                "741895.6203",
                "741895.6203",
                "741895.6203",
                "741895.6203",
                "741895.6203",
                "741895.6203",
                "741895.6203",
                "741895.6203",
                "741895.6203",
                "741895.6203",
                "741895.6203",
                "741895.6203",
                "741895.6203",
                "741895.6203",
                "741895.6203",
                "741895.6203",
                "741895.6203",
                "741895.6203",
                "741895.6203",
                "741895.6203"
            ],
            "Processed": [
                "741895.6203",
                "741895.6203",
                "741895.6203",
                "741895.6203",
                "741895.6203",
                "741895.6203",
                "741895.6203",
                "741895.6203",
                "741895.6203",
                "741895.6203",
                "741895.6203",
                "741895.6203",
                "741895.6203",
                "741895.6203",
                "741895.6203",
                "741895.6203",
                "741895.6203",
                "741895.6203",
                "741895.6203",
                "741895.6203",
                "741895.6203",
                "741895.6203",
                "741895.6203",
                "741895.6203",
                "741895.6203",
                "741895.6203",
                "741895.6203",
                "741895.6203",
                "741895.6203",
                "741895.6203"
            ]
        },
        "Small": {
            "Unprocessed": [
                "875639240.1",
                "875639240.1",
                "875639240.1",
                "875639240.1",
                "875639240.1",
                "875639240.1",
                "875639240.1",
                "875639240.1",
                "875639240.1",
                "875639240.1",
                "873639240.1",
                "875639240.1",
                "875639240.1",
                "875639240.1",
                "875639240-1",
                "875639240.1",
                "875639240.1",
                "875639240.1",
                "875639240.1",
                "875639240.1",
                "875639240.1",
                "873639240.1",
                "3756392-0.1",
                "873639240.1",
                "875639240.1",
                "873639240.1",
                "875639240.1",
                "87563924041",
                "87563924041",
                "3736392-0.1"
            ],
            "Processed": [
                "375639240.1",
                "8756392-0.1",
                "875639240-1",
                "8756392-0.1",
                "375639240.1",
                "875639240.1",
                "875639240.1",
                "875639240-1",
                "875639240.1",
                "875639240.1",
                "875639240.1",
                "875639240.1",
                "875639240.1",
                "8756392-0.1",
                "875639240.1",
                "875639240.1",
                "3756392-0.1",
                "875639240.1",
                "875639240.1",
                "875639240.1",
                "875639240.1",
                "8736392-0-1",
                "8756392-0-1",
                "875639240.1",
                "875639240.1",
                "875639240.1",
                "8756392-0.1",
                "875639240.1",
                "875639240-1",
                "3736392-0.1"
            ]
        }
    },
    {
        "Image code": "40",
        "Big": {
            "Unprocessed": [
                "856072.493.1",
                "856072.4931",
                "856072.4931",
                "856072-4931",
                "856072.4931",
                "856072.4931",
                "856072-4931",
                "856072.4931",
                "856072.4931",
                "856072.4931",
                "856072.4931",
                "856072-4931",
                "856072.4931",
                "856072.4931",
                "856072.4931",
                "856072.4931",
                "856072.4931",
                "856072-4931",
                "8560724938.",
                "856072.4931",
                "856072.4931",
                "856072.4931",
                "856072.4931",
                "856072.4931",
                "856072.4931",
                "8560724311",
                "856072.4931",
                "856072.4931",
                "85-60722-49+31",
                "856072.24931"
            ],
            "Processed": [
                "856072.4931",
                "856072.4931",
                "856072.4931",
                "856072.4931",
                "856072.4931",
                "856072.4931",
                "856072.4931",
                "856072.4931",
                "856072.4931",
                "856072.4931",
                "856072.4931",
                "856072.4931",
                "856072.4931",
                "856072.4931",
                "856072.4931",
                "856072.4931",
                "856072.4931",
                "856072.4931",
                "856072.4931",
                "856072.4931",
                "856072.4931",
                "856072.4931",
                "856072.4931",
                "856072.4931",
                "856072.4931",
                "856072.4931",
                "856072.4931",
                "856072.4931",
                "856072.4931",
                "856072.4931"
            ]
        },
        "Medium": {
            "Unprocessed": [
                "0258354.671",
                "0258394671",
                "0258394.671",
                "6258.39-4672",
                "0256394.672",
                "0258394.671",
                "0258354.671",
                "0256394671",
                "0258394.671",
                "025-8394.671",
                "0258354.671",
                "0258394.671",
                "0258394.671",
                "0258394.671",
                "0256394.671",
                "025-9394.671",
                "0256354.671",
                "0266354677.9",
                "0258394.671",
                "0258354.671",
                "0256394.671",
                "0258354671",
                "0258394.671",
                "0258394.671",
                "0258394.671",
                "0258394.671",
                "0258394.671",
                "0256394.671",
                "0258354.671",
                "0256394.671"
            ],
            "Processed": [
                "0258394.671",
                "0258394.671",
                "0258394.671",
                "0258394.671",
                "0258394671",
                "0258394-671",
                "0258394671",
                "0258394671",
                "0258394.671",
                "0258394.671",
                "0258394.671",
                "0258394.671",
                "0258394.671",
                "0258394.671",
                "0258394.671",
                "0258394.671",
                "0258394.671",
                "0258394.671",
                "0258394.671",
                "0258394671",
                "0258394.671",
                "0258394671",
                "0258394.671",
                "0258394.671",
                "0258394.671",
                "0258394.671",
                "0258394.671",
                "0258394.671",
                "0258394.671",
                "0258394.671"
            ]
        },
        "Small": {
            "Unprocessed": [
                "",
                "",
                "",
                "",
                ".-.-...-.--.51-5215.262...89.5232-..15",
                "32...7-..7-..--..-2..5..-...-.1.......35-52.53.53",
                "1..8....7-2--...785...3--610..8.11..1255552-723",
                "",
                "",
                "",
                "",
                "",
                "",
                "675.850567.55",
                "9512943.69-",
                "65.5586686",
                "658.5.-83.69",
                "95.125-43.69",
                ".85.12843.69",
                "652958369",
                "",
                "85124343.69",
                "95.12043753",
                "65.62.-9-13+-63",
                "63.39588",
                "95.2043.65",
                "95.12043759",
                "",
                "675.-639332.553",
                "56.039-15155"
            ],
            "Processed": [
                "85.08.69",
                "85.12043.69",
                "85.1288.68",
                "85.02843.68",
                "85.0288.68",
                "85.0208.58",
                "85.12043.69",
                "85.0208.69",
                "85284358",
                "85801359",
                "85.02843.69",
                "85803358",
                "85.0280859",
                "95.12043-59",
                "8512843.69",
                "9590869",
                "9512043.69",
                "85883369",
                "85.18343.69",
                "85.12043.69",
                "85.12033.69",
                "8512843.59",
                "8512843.69",
                "9512843.69",
                "85.12843.69",
                "85.12043.69",
                "8512043.69",
                "5512843-69",
                "9512043.69",
                "8512843769"
            ]
        }
    },
    {
        "Image code": "41",
        "Big": {
            "Unprocessed": [
                "71.680135942",
                "766860135942",
                "70.680135942",
                "71.68.0135942",
                "72.6.80135942",
                "7-66335941-",
                "7.680135942",
                "7.680135942",
                "7+680135942",
                "73..680135942",
                "7..680135942",
                "7.6-810135942",
                "7..6810135942",
                "72..680135942",
                "7..680135942",
                "72.680135942",
                "7..680135942",
                "77.680135942",
                "7..680.-35942",
                "7.680135942",
                "716807135942",
                "7.6-8013594.2",
                "77.68013-5942",
                "7..68013-5942",
                "77.680135942",
                "7.68.0135942",
                "71..680135942",
                "7.68.0135942",
                "7.68013-5942",
                "7+680.13-5942"
            ],
            "Processed": [
                "7.680135942",
                "-1.680.-35942",
                "7.680135942",
                "7.680135942",
                "-1.680.-35942",
                "7.680.-35942",
                "7.680135942",
                "-1.680.-35942",
                "7.680135942",
                "7.680135942",
                "7.680135942",
                "7.680135942",
                "7.680135942",
                "7.680135942",
                "7.680135942",
                "-1.680.-35942",
                "7.680.-35942",
                "7.680135942",
                "-.-.680.-35942",
                "-1.680.-35942",
                "-1.680.-35942",
                "7.680.-35942",
                "7.680135942",
                "-1.680.-35942",
                "7.6130135942",
                "-1.680.-35942",
                "7.680135942",
                "7.680.-35942",
                "-1.680.-35942",
                "7.6130135942"
            ]
        },
        "Medium": {
            "Unprocessed": [
                "5.57701.2.6432",
                "1.54-1-.-24.1-2",
                "5.5.701.25439",
                "534--1-1--.1-2",
                "9...-445--29",
                "1--4435836",
                "5.93701-2-6438",
                "5554-1--1.-19",
                "",
                "5.5.701.26439",
                "5.5-701.26.--139",
                "5857701-26439",
                "5.-3701.2.6-.-.119",
                "554425--29",
                "",
                "5.973126439",
                "5.5771312.6439",
                "5.5701-2-6439",
                "55.226--2.-1-",
                "",
                "..-544-6-3..-.-",
                "5...3701-26432",
                ".554.25.-.1+9",
                "5.5970126439",
                "",
                "544-6-1-.11-",
                "5-42-19.32",
                "5.57731-26439",
                "5657011.2.6-139",
                "5541-.-1"
            ],
            "Processed": [
                "5.970126435",
                "5.371.7126438",
                "5.971.7126436",
                "5.971.7126438",
                "5.971.7126436",
                "5.970126436",
                "5.970126436",
                "5.970126436",
                "5.970126436",
                "5.970126436",
                "5.971.7126436",
                "5.970126435",
                "5.970126436",
                "5.971.7126438",
                "5.971.7126436",
                "5.970126436",
                "5.970126436",
                "5.9701264313",
                "5.971.7126436",
                "5.9713126436",
                "5.970126438",
                "5.370126438",
                "5.970126438",
                "5.97131264313",
                "5.970126436",
                "5.971.71264319",
                "5.370126436",
                "5.970126438",
                "5.9701264313",
                "5.970126436"
            ]
        },
        "Small": {
            "Unprocessed": [
                "",
                "-515.7.5-.423735",
                "-2.--.+1---1-.11.-.6--3.1.-..1-",
                "",
                "167823.4-+-.727-35",
                "6.8.-753.4-.227935",
                "15-11.6-933335",
                "6-6613.-8.13365",
                "6-99429735",
                "6.1110-16-2.166",
                "67--23.42927155",
                "121-311-1-.-2-721-2",
                "",
                "6-118555-60..7275-5",
                ".-.-.-+--.--.-69..-1-.1+23-.1.-15",
                "",
                "",
                "1-..-1.6-33.423735",
                "",
                "-61-81-11.4-11.1-7.-.-5",
                "9-2-7653.9-23755",
                "",
                "2.-1.-239-.-...73755",
                "-.1.-86-1-+--1---.03-1.-+1-",
                "",
                "2.-230-1-1---135.",
                "5+159.92+3755",
                "6.71-5--.4-5-15--1.1..5-.",
                "",
                ""
            ],
            "Processed": [
                "6139-4213-35",
                "6.9-451.4--1-.-.--.-35",
                "5739420-35",
                "6.5-411.4-12-35",
                "5139.42--3--35",
                "6139.4213735",
                "6-939.4213--35",
                "6.9-411.4-1-.--35",
                "",
                "5139.4213--35",
                "5-939.42-3-35",
                "6-739.4-393735",
                "6939.4213735",
                "51-411.4--1-.-.--.-35",
                "6133.420-735",
                "55-411.4-1-.-.--35",
                "6939.46-3-.3-5",
                "6.9-411.4--1-.-.--+3-5",
                "5-939.4213735",
                "5-939.4-33-35",
                "5.--111.4--12-.-3-5",
                "6.5-411.4--1-.-2-3-.1",
                "613942-3-35",
                "5133.4213735",
                "6939-4-33735",
                "5133.4-3-3--35",
                "-+--111.4--1-.-9-3-.1",
                "6133.4213--35",
                "6-933.4293-135",
                "6.6-411-4-1-.-.--.-35"
            ]
        }
    },
    {
        "Image code": "42",
        "Big": {
            "Unprocessed": [
                ".1..-21.51..-.1-3.-..-21..-.-.........-..52",
                "",
                "",
                ".-.---..-..--21.5......2.-....-...-.-.30....--",
                ".1..-1-..1-..3-.-.15212.91.......5-61-6..1.-33.--..2.",
                ".-.-7132-..5...3.5..-.-.-1-.6922-52.-2",
                "0.7.-.--..-.1.6--.1.-3...1..-.-.-..-.2..-.7....5..1.5..6122.",
                "",
                "",
                "",
                ".1..2.1.......5.26-.-231.2...5-.2..1.-9.-.2...3...-.5-.-.2",
                "",
                "",
                "",
                "1--.-.-..--.-.2..2....3-.-3..2-4-.....210..2...-.5-6132",
                "",
                "",
                "-.-.5-.....5-12.093..-65.6.-.63....5.-...-..-----61",
                "1..-11..1-..72.5-..5-11-.-7..67.--2.-...29-12..2",
                "",
                "11-.-1-3...-..2-.11...31.-.359.6-.323.......-20......1-",
                "211.192.-.52211-.1..21....-...11-.-1..3.15...1.2..5.-5.-53",
                "",
                "2.5..5.1.7-..-...3..011.-777.-6.-725-.-.3...........-.-16-2-3.53-",
                "",
                "",
                "09.-.2..-..-.1-2-25-13...57-.....5.....7-...15.-3-.236...-.5",
                "",
                "",
                ""
            ],
            "Processed": [
                "0198-.276453",
                "0198.276453",
                "0198.2764-53",
                "0198.276453",
                "0198.276453.",
                "0198..276453",
                "0198..276453",
                "0198.27645.3",
                "0198.276.453.+",
                "0198.276453",
                "0198.27645..3",
                "0198.276453",
                "01-98..276453",
                "0198.276453",
                "0198..276453",
                "0198.276453",
                "0198.276453",
                "0198..276453",
                "0198.276453",
                "0198.276453",
                "01.98.276453",
                "0198.276453",
                "0198.276453",
                "0198.276453",
                "0198.276453",
                "01982.276453",
                "01198.276453",
                "0.1985-276453",
                "0198.276453",
                "0198.276453"
            ]
        },
        "Medium": {
            "Unprocessed": [
                "",
                "-..595...3..33.1-.2-..-1.-.",
                ".-55.-..391.1-6.-5.",
                "--5--...1.-.2.5-......42.",
                "1555.35552",
                "-5-.5-...-.-...-1...5-..-..-...-",
                "",
                ".5---.1....3531-2-.11..56",
                "--3.674.---.-72",
                "",
                "",
                "---",
                "",
                "...-5-.-....2...1.31.6...97.6...2-...3.1",
                ".237.2--22....-2--+.5.-........53",
                "",
                "-32-..361.-12.-.2-7..-..-..-5.-657.",
                "-.35.15-....-...-.-..5......2",
                "--.-333-3",
                ".29152..-7.1..-.3.5-",
                "--3133.2.1-......9.2...3-..75",
                ".-..-5.552..-.6...15......25.-5",
                "52.2..9-.5.-.5-.53....-..",
                "....3..3.2....-.2.5-.-....3..57",
                ".-.2327323",
                "-..5.2..3..2.-5..3.-.-.--5-.-5",
                ".2..5.1-.1..2-.-3..-9-.--..-..-.-5-.-",
                "",
                "",
                "7...3.53121.6.7...-5.5.333"
            ],
            "Processed": [
                "736912.0485",
                "736512.0485",
                "7-.-36512.0.85",
                "736912.0485",
                "796-92.085",
                "736912.0485",
                "736912.0485",
                "7.96912.0485",
                "736912.0485",
                "7365112.0485",
                "736972.0485",
                "736512.0485",
                "736912.0485",
                "-.-36912.0485",
                "736512.06185",
                "736512.0485",
                "-136512-.0485",
                "...136912.0485",
                "736512.0485",
                "7369-12.0485",
                "736912.0485",
                "736912.0485",
                "-736912.0485",
                "736912.085",
                "736512.-0485",
                "736912.0485",
                "736512.0485",
                "796512.0485",
                "736912.0485",
                "736912-.0485"
            ]
        },
        "Small": {
            "Unprocessed": [
                "--",
                "5",
                "",
                "-..--",
                ".-.-.",
                "...",
                ".",
                "...-.32-",
                "...",
                "",
                "-.",
                "-...-",
                ".",
                "",
                "-..-55.--",
                "-.--..5-.",
                "-.",
                ".--.",
                ".-.1.5.-",
                "-.5....7-...",
                ".-5-.-.1...",
                "--...-.-.",
                "....5-...",
                "...--...--.",
                "--.---",
                "...-53.1...--",
                "-..56...-.-",
                "....",
                ".-.",
                "....."
            ],
            "Processed": [
                "6023.958",
                ".6123.8",
                "",
                "",
                "",
                "7593.960",
                "",
                "7563.9-60",
                "7563.960",
                "7583.950",
                "",
                "75123850",
                "",
                "76123.958",
                "",
                "76123.868",
                "",
                ".1612-3.968",
                "",
                "7583.858",
                ".-5623.050",
                "",
                "7583050",
                "",
                "7563.960",
                "",
                "",
                "",
                "",
                ""
            ]
        }
    },
    {
        "Image code": "43",
        "Big": {
            "Unprocessed": [
                "---",
                ".",
                "------",
                ".-.-.-.-",
                "..----",
                "--.",
                ".-..-..-4..-..-.-",
                "---.-.---",
                "-.--",
                "..--..--",
                "---..",
                ".--...-",
                ".--.-",
                "1......-....-5..--.1-.",
                "",
                "--.-.--..-",
                "-....-.-...--.-.0-..-.---..-",
                "--0..-6--.---.---.2......-.-.",
                "",
                "-.......-....3-..-.-.2...3...5....",
                ".-5...--...-0-1.-0.-------...",
                "5.-..-..-1.-5--..-.1-.-...1.--.6",
                ".---.-6...-.-9.-..7-.-5.1.-.-.-.--.",
                "-.1.--..--..--4-...3.....3",
                ".5...--.-1-.--.--...-5.-.",
                "..5.---...-..-3....-.--.-....-2...1.-..",
                ".1..----.-...-.-.-57--",
                ".2...5..----.-..-.2.-",
                ".----.---",
                ".--.......-.5.3..7.-.-..-....-.-.-."
            ],
            "Processed": [
                "34591627.80",
                "34591627.80",
                "34591627.80",
                "34591627.80",
                "34591627.80",
                "34591627.80",
                "34591627.80",
                "34591627.80",
                "34591627.80",
                "34591627.80",
                "34591627.80",
                "34591627.80",
                "34591627.80",
                "34591627.80",
                "34591627.80",
                "34591627.80",
                "34591627.80",
                "34591627.80",
                "34591627.80",
                "34591627.80",
                "34591627.80",
                "34591627.80",
                "34591627.80",
                "34591627.80",
                "34591627.80",
                "34591627.80",
                "34591627.80",
                "34591627.80",
                "34591627.80",
                "34591627.80"
            ]
        },
        "Medium": {
            "Unprocessed": [
                ".",
                "---",
                "..--",
                "7------.-",
                "-.-",
                ".-.",
                "..",
                ".",
                "--.-",
                "....-.",
                "5---------..-",
                "--.",
                ".-0",
                ".--..5-....-..1.-...",
                ".-..-.-....-6..",
                ".---",
                "........5.--",
                ".-..-..",
                ".-..-..-",
                "-..--",
                ".-.6-.-.3-",
                "-...-",
                "-.---.",
                "-....-..-",
                "..",
                "----",
                "-.---.---3.",
                ".-5..6--..-.--.",
                "----.",
                "..-...2--."
            ],
            "Processed": [
                "12.08365754",
                "12.08369754",
                "12.08369754",
                "12.06369754",
                "12.08369754",
                "12.08369754",
                "12.08365754",
                "12.08369754",
                "12.08369754",
                "12.08369754",
                "12.06369754",
                "12.08369754",
                "12.08369754",
                "12.08369754",
                "12.08369754",
                "12.08369754",
                "12.08369754",
                "12.08369754",
                "12.08369754",
                "12.08369754",
                "12.08369754",
                "12.08365754",
                "12.06369754",
                "12.08369754",
                "12.0859754",
                "12.08369754",
                "12.08369754",
                "12.08365754",
                "12.08369754",
                "12.08369754"
            ]
        },
        "Small": {
            "Unprocessed": [
                "83459620",
                "93459620",
                "83459620",
                "93459620",
                ".",
                "9345620",
                "",
                ".",
                ".",
                "83459620.7",
                "83459620",
                "",
                "83459620",
                ".",
                "83459620.7",
                ".",
                "..",
                ".",
                ".",
                "83459620",
                ".",
                "",
                "",
                "-.",
                "-",
                "-",
                ".",
                "-.",
                ".",
                ".."
            ],
            "Processed": [
                "93459620",
                "93459620",
                "83459620",
                "93459620",
                "93459621.7",
                "93459620",
                "83459620",
                "93459620",
                "83459620",
                "83459620.7",
                "83459620",
                "93459621.7",
                "83459620",
                "83459620",
                "83459620.7",
                "93459620",
                "83459620",
                "83459620",
                "83459620.7",
                "83459620",
                "834596267",
                "93459620",
                "834596267",
                "83459628",
                "83459520",
                "83459620",
                "83459620",
                "83459620",
                "83459620",
                "83459620"
            ]
        }
    }
]