[{
    "Lens": "daheng_6mm",
    "Distance": "35",
    "Horizontal angle": "60",
    "Vertical angle": "60",
    "Lighting conditions": "3",
    "Screen brightness": "50"
},
{
    "Image code": "00",
    "Big": {
        "Unprocessed": [
            "23.97460518",
            "23.97460518",
            "23.97460518",
            "23.97460518",
            "23.97460518",
            "23.97460518",
            "23.97460518",
            "23.97460518",
            "23.97460518",
            "23.97460518",
            "23.97460518",
            "23.97460518",
            "23.97460518",
            "23.97460518",
            "23.97460518",
            "23.97460518",
            "23.97460518",
            "23.97460518",
            "23.97460518",
            "23.97460518",
            "23.97460518",
            "23.97460518",
            "23.97460518",
            "23.97460518",
            "23.97460518",
            "23.97460518",
            "23.97460518",
            "23.97460518",
            "23.97460518",
            "23.97460518"
        ],
        "Processed": [
            "23.97460518",
            "23.97460518",
            "23.97460518",
            "23.97460518",
            "23.97460518",
            "23.97460518",
            "23.97460518",
            "23.97460518",
            "23.97460518",
            "23.97460518",
            "23.97460518",
            "23.97460518",
            "23.97460518",
            "23.97460518",
            "23.97460518",
            "23.97460518",
            "23.97460518",
            "23.97460518",
            "23.97460518",
            "23.97460518",
            "23.97460518",
            "23.97460518",
            "23.97460518",
            "23.97460518",
            "23.97460518",
            "23.97460518",
            "23.97460518",
            "23.97460518",
            "23.97460518",
            "23.97460518"
        ]
    },
    "Medium": {
        "Unprocessed": [
            "8547928106",
            "35+7928106",
            "35+7928106",
            "3547928106",
            "85+7928106",
            "354.7928106",
            "35+7928106",
            "35477928106",
            "85+.7928106",
            "357928106",
            "85+7928106",
            "857928106",
            "35+7928106",
            "854.7928106",
            "8547928106",
            "85+7928106",
            "55+7928106",
            "854.7928106",
            "35+7928106",
            "8547928106",
            "354.7928106",
            "35+7928106",
            "354.7928106",
            "35+.7928106",
            "35+.7928106",
            "35+7928106",
            "85+7928106",
            "35+7928106",
            "85+7928106",
            "35+7928106"
        ],
        "Processed": [
            "87928106",
            "357928106",
            "37928106",
            "357928106",
            "8547928106",
            "347928106",
            "3547925106",
            "357928106",
            "37928106",
            "37926106",
            "37928106",
            "557928106",
            "37028106",
            "3547926106",
            "3547928106",
            "367928108",
            "5547928106",
            "377928106",
            "367928106",
            "8647928106",
            "3547928106",
            "387928106",
            "3547928106",
            "8647028106",
            "367928106",
            "5647928106",
            "854.7928108",
            "857928106",
            "85477928106",
            "347928106"
        ]
    },
    "Small": {
        "Unprocessed": [
            "01865",
            "012765",
            "012798365",
            "46",
            "4",
            "0412.788385",
            "012788385",
            "47",
            "0412798385",
            "012798365",
            "0413798385",
            "013798385",
            "475",
            "45",
            "4",
            "8",
            "0178365",
            "012788365",
            "012788365",
            "04412798365",
            "012798365",
            "012788365",
            "0788",
            "0412798365",
            "012788365",
            "012738365",
            "4",
            "0412.798365",
            "01865",
            "465"
        ],
        "Processed": [
            "0",
            "0",
            "01",
            "0",
            "0",
            "0",
            "02785",
            "0",
            "+",
            "04127987654",
            "645",
            "40",
            "4",
            "08-",
            "04",
            "0",
            "012865",
            "4+5",
            "415",
            "0875",
            "0127986",
            "0",
            "0",
            "4178",
            "017",
            "015",
            "0",
            "0765",
            "00",
            "0"
        ]
    }
},
{
    "Image code": "01",
    "Big": {
        "Unprocessed": [
            "7.635908142",
            "7.635908142",
            "7.635908142",
            "7.655908142",
            "7.655908142",
            "7.635908142",
            "7.635908142",
            "7.635908142",
            "7.635908142",
            "7.635908142",
            "7.635908142",
            "7.635908142",
            "7.635908142",
            "7.635908142",
            "7.635908142",
            "7.635908142",
            "7.635908142",
            "7.635908142",
            "7.655908142",
            "7.635908142",
            "7.635908142",
            "7.635908142",
            "7.655908142",
            "7.635908142",
            "7.635908142",
            "7.635908142",
            "7.635908142",
            "7.635908142",
            "7.635908142",
            "7.635908142"
        ],
        "Processed": [
            "7055908142",
            "7055908142",
            "7055908142",
            "7.635908142",
            "7055908142",
            "7.635908142",
            "7055908142",
            "7055908142",
            "7055908142",
            "7.635908142",
            "7055908142",
            "7655908142",
            "7055908142",
            "7055908142",
            "7055908142",
            "7085908142",
            "7085908142",
            "7655908142",
            "7.635908142",
            "7.635908142",
            "7.635908142",
            "7.055908142",
            "7055908142",
            "7655908142",
            "7055908142",
            "7085908142",
            "7085908142",
            "7085908142",
            "7055908142",
            "7085908142"
        ]
    },
    "Medium": {
        "Unprocessed": [
            "4210.568937",
            "4210.568937",
            "4210.568937",
            "4210.568937",
            "4210.568937",
            "4210.568937",
            "4210.568937",
            "4210.568937",
            "4210.568937",
            "4210.568937",
            "4210.568937",
            "4210.568937",
            "4210.568937",
            "4210.568937",
            "4210.568937",
            "4210.568937",
            "4210.568937",
            "4210.568937",
            "4210.568937",
            "4210.568937",
            "4210.568937",
            "4210.568937",
            "4210.568937",
            "4210.568937",
            "4210.568937",
            "4210.568937",
            "4210.568937",
            "4210.568937",
            "4210.568937",
            "4210.568937"
        ],
        "Processed": [
            "4210.568937",
            "4210.568937",
            "4210.568937",
            "4210.568937",
            "4210.568937",
            "4210.568937",
            "4210.568937",
            "4210.568937",
            "4210.568937",
            "4210.568937",
            "4210.568937",
            "4210.568937",
            "4210.568937",
            "4210.568937",
            "4210.568937",
            "4210.568937",
            "4210.568937",
            "4210.568937",
            "4210.568937",
            "4210.568987",
            "4210.568937",
            "4210.568937",
            "4210568937",
            "4210.568937",
            "4210.568937",
            "4210.568937",
            "4210.568937",
            "4210.568937",
            "4210.568987",
            "4210.568937"
        ]
    },
    "Small": {
        "Unprocessed": [
            "48",
            "35",
            "98",
            "488+",
            "487",
            "947",
            "488",
            "48.7",
            "465027",
            "35",
            "78.7",
            "35",
            "48",
            "35",
            "48.7",
            "48",
            "35",
            "3",
            "4827",
            "35",
            "35",
            "4",
            "3",
            "487",
            "4",
            "468",
            "7888",
            "4827",
            "48",
            "47"
        ],
        "Processed": [
            "4",
            "4",
            "76807",
            "4207",
            "48",
            "3",
            "3",
            "3",
            "7247",
            "5",
            "3",
            "3",
            "4",
            "6",
            "0.",
            "48",
            "42",
            "35",
            "45",
            "4",
            "3",
            "3",
            "4",
            "4",
            "3",
            "407",
            "45",
            "46",
            "4",
            "4"
        ]
    }
},
{
    "Image code": "02",
    "Big": {
        "Unprocessed": [
            "2",
            "2",
            "28",
            "2",
            "",
            "8",
            "2",
            "2",
            "3",
            "2",
            "2",
            "5",
            "2",
            "3",
            "2",
            "",
            "28",
            "",
            "2",
            "28",
            "22",
            "2",
            "",
            "",
            "2",
            "3",
            "",
            "1",
            "",
            "3"
        ],
        "Processed": [
            "4150578962",
            "430578962",
            "4130578962",
            "4130578962",
            "4180578962",
            "41805789.62",
            "4150578962",
            "41805759.62",
            "4130578962",
            "41805789.62",
            "41505789.62",
            "4805789.62",
            "4305789.62",
            "480578962",
            "4150576062",
            "41505780.62",
            "4130578962",
            "4805780.62",
            "450578962",
            "41305789.62",
            "480578962",
            "450575962",
            "4130578962",
            "4130578062",
            "430578962",
            "480578062",
            "480578962",
            "4805789.62",
            "4150578062",
            "4505780.62"
        ]
    },
    "Medium": {
        "Unprocessed": [
            "",
            "",
            "1",
            "",
            "",
            "5",
            "",
            "2",
            "",
            "2",
            "3",
            "2",
            "5",
            "3",
            "",
            "2",
            "",
            "",
            "3",
            "22",
            "",
            "",
            "1",
            "2",
            "3",
            "2",
            "2",
            "2",
            "3",
            "8"
        ],
        "Processed": [
            "464",
            "464",
            "065+",
            "0065",
            "46",
            "4886",
            "4",
            "4316",
            "088",
            "46",
            "4",
            "40",
            "4",
            "4",
            "06",
            "0165",
            "365",
            "47",
            "4",
            "46",
            "48",
            "47",
            "44",
            "488",
            "48",
            "4",
            "48",
            "4",
            "33",
            "46"
        ]
    },
    "Small": {
        "Unprocessed": [
            "2",
            "5",
            "1",
            "2",
            "2",
            "",
            "",
            "5",
            "1",
            "5",
            "5",
            "",
            "1",
            "5",
            "1",
            "",
            "3",
            "2",
            "",
            "1",
            "2",
            "",
            "",
            "2",
            "2",
            "",
            "5",
            "",
            "5",
            "2"
        ],
        "Processed": [
            "38",
            "8",
            "3",
            "8",
            "4",
            "3",
            "3",
            "3",
            "4",
            "4",
            "34",
            "48",
            "4",
            "3",
            "3",
            "31",
            "4",
            "3",
            "34",
            "3",
            "3",
            "8",
            "2",
            "4",
            "3",
            "8",
            "38",
            "8",
            "3",
            "4"
        ]
    }
},
{
    "Image code": "03",
    "Big": {
        "Unprocessed": [
            "9806.135724",
            "9806.135724",
            "9806.135724",
            "9806.135724",
            "9806.135724",
            "9806.135724",
            "9806.135724",
            "9806.135724",
            "9806.135724",
            "9806.135724",
            "9806.135724",
            "9806.135724",
            "9806.135724",
            "9806.135724",
            "9806.135724",
            "9806.135724",
            "9806.135724",
            "9806.135724",
            "9806.135724",
            "9806.135724",
            "9806.135724",
            "9806.135724",
            "9806.135724",
            "9806.135724",
            "9806.135724",
            "9806.135724",
            "9806.135724",
            "9806.135724",
            "9806.135724",
            "9806.135724"
        ],
        "Processed": [
            "9806.135724",
            "9806.135724",
            "9806.135724",
            "9806.135724",
            "9806.135724",
            "9806.135724",
            "9806.135724",
            "9806.135724",
            "9806.135724",
            "9806.135724",
            "9806.135724",
            "9806.135724",
            "9806.135724",
            "9806.135724",
            "9806.135724",
            "9806.135724",
            "9806.135724",
            "9806.135724",
            "9806.135724",
            "9806.135724",
            "9806.135724",
            "9806.135724",
            "9806.135724",
            "9806.135724",
            "9806.135724",
            "9806.135724",
            "9806.135724",
            "9806.135724",
            "9806.135724",
            "9806.135724"
        ]
    },
    "Medium": {
        "Unprocessed": [
            "76576428980",
            "7676423980",
            "7616.423980",
            "7676425980",
            "7576425980",
            "7516423980",
            "7516425980",
            "7576.4423980",
            "7516425980",
            "7616.425980",
            "7516423980",
            "76576425980",
            "7576423980",
            "7576425980",
            "7576423980",
            "7516+25980",
            "76516423980",
            "7516423980",
            "7516425980",
            "7576423980",
            "7516423980",
            "7576428980",
            "7516.425980",
            "7576423980",
            "7576425980",
            "7616.425980",
            "76516.423980",
            "7576423980",
            "7676423980",
            "7576423980"
        ],
        "Processed": [
            "7516423980",
            "7516+23980",
            "7616423980",
            "7516+25980",
            "7516425980",
            "7516423980",
            "7516425980",
            "7516.423980",
            "7516425980",
            "7516423980",
            "7516+25980",
            "7516425980",
            "7516423950",
            "7516425980",
            "7516423980",
            "7516425980",
            "7516.425980",
            "7516.423980",
            "7516+23980",
            "7516423980",
            "7516423980",
            "7516425950",
            "7516425980",
            "7516+23980",
            "7516425980",
            "7516425980",
            "7516423980",
            "7516423980",
            "7516+23980",
            "75164+23980"
        ]
    },
    "Small": {
        "Unprocessed": [
            "88",
            "88",
            "97",
            "81",
            "8",
            "885",
            "880",
            "80",
            "40",
            "85",
            "80",
            "861",
            "88",
            "8",
            "8",
            "88",
            "48",
            "88",
            "888",
            "8",
            "8",
            "86",
            "88",
            "86",
            "885",
            "8",
            "4",
            "85",
            "885",
            "8885"
        ],
        "Processed": [
            "685",
            "08",
            "885",
            "8",
            "4",
            "85",
            "88",
            "88",
            "80",
            "8",
            "88",
            "48",
            "381",
            "885",
            "8",
            "885",
            "08",
            "485",
            "805",
            "885",
            "88",
            "48",
            "88",
            "8",
            "48",
            "86",
            "8",
            "85",
            "480",
            "4"
        ]
    }
},
{
    "Image code": "10",
    "Big": {
        "Unprocessed": [
            "8.654139702",
            "8.654139702",
            "8.654139702",
            "8.654139702",
            "8.654139702",
            "8.654139702",
            "8.654139702",
            "8.654139702",
            "8.654139702",
            "8.654139702",
            "8.654139702",
            "8.654139702",
            "8.654139702",
            "8.654139702",
            "8.654139702",
            "8.654139702",
            "8.654139702",
            "8.654139702",
            "8.654139702",
            "8.654139702",
            "8.654139702",
            "8.654139702",
            "8.654139702",
            "8.654139702",
            "8.654139702",
            "8.654139702",
            "8.654139702",
            "8.654139702",
            "8.654139702",
            "8.654139702"
        ],
        "Processed": [
            "8.654139702",
            "8.654139702",
            "8.654139702",
            "8.654139702",
            "8.654139702",
            "8.654139702",
            "8.654139702",
            "8.654139702",
            "8.654139702",
            "8.654139702",
            "8.654139702",
            "8.654139702",
            "8.654139702",
            "8.654139702",
            "8.654139702",
            "8.654139702",
            "8.654139702",
            "8.654139702",
            "8.654139702",
            "8.654139702",
            "8.654139702",
            "8.654139702",
            "8.654139702",
            "8.654139702",
            "8.654139702",
            "8.654139702",
            "8.654139702",
            "8.654139702",
            "8.654139702",
            "8.654139702"
        ]
    },
    "Medium": {
        "Unprocessed": [
            "10638547.92",
            "10638547.92",
            "10638547.92",
            "10638547.92",
            "10638547.92",
            "10638547.92",
            "10638547.92",
            "10638547.92",
            "106385+7.92",
            "10638547.92",
            "10638547.92",
            "10638547.92",
            "10638547.92",
            "10638547.92",
            "10638547.92",
            "10638547.92",
            "10638547.92",
            "106385+7.92",
            "10638547.92",
            "106385+7.92",
            "10638547.92",
            "10638547.92",
            "10638547.92",
            "106385+7.92",
            "10638547.992",
            "10638547.92",
            "10638547.92",
            "10638547.92",
            "10638547.92",
            "10638547.92"
        ],
        "Processed": [
            "10638547.92",
            "10638541.92",
            "10688547.92",
            "10638547.92",
            "106385+7.92",
            "1069854792",
            "10698547.92",
            "10638547.92",
            "10698547.92",
            "1069854792",
            "10688547.92",
            "1069857.92",
            "10638547.92",
            "1068857.02",
            "10688547.92",
            "10638547.92",
            "10688547.92",
            "10688547.92",
            "10638547.92",
            "106985792",
            "10638547.92",
            "1063854792",
            "1069854792",
            "106885792",
            "1068857.92",
            "1069854792",
            "1068857.92",
            "1063857.92",
            "106885792",
            "70638547.92"
        ]
    },
    "Small": {
        "Unprocessed": [
            "76015",
            "8875",
            "7601+25",
            "8885",
            "8601295",
            "888",
            "7680125",
            "70125",
            "76015",
            "7601+25",
            "36015",
            "3601+25",
            "7601+25",
            "760125",
            "760125",
            "7601+95",
            "7875",
            "3601+5",
            "85",
            "7601+95",
            "760145",
            "76901+25",
            "76601+25",
            "761",
            "76501095",
            "8875",
            "76012",
            "85601295",
            "36501+295",
            "88725"
        ],
        "Processed": [
            "4184",
            "3++",
            "8+",
            "004",
            "30",
            "8+",
            "301",
            "80",
            "7+",
            "8",
            "3",
            "00",
            "++15",
            "7+",
            "01",
            "0+",
            "7",
            "04",
            "44",
            "70+",
            "8+",
            "01+",
            "2",
            "80",
            "84",
            "84",
            "8+",
            "8+",
            "304",
            "70"
        ]
    }
},
{
    "Image code": "11",
    "Big": {
        "Unprocessed": [
            "09458.16723",
            "09458.16723",
            "09458.16723",
            "09458.16723",
            "09458.16723",
            "09458.16723",
            "09458.16723",
            "09458.16723",
            "09458.16723",
            "09458.16723",
            "09458.16723",
            "09458.16723",
            "09458.16723",
            "09458.16723",
            "09458.16723",
            "09458.16723",
            "09458.16723",
            "09458.16723",
            "09458.16723",
            "09458.16723",
            "09458.16723",
            "09458.16723",
            "09458.16723",
            "09458.16723",
            "09458.16723",
            "09458.16723",
            "09458.16723",
            "09458.16723",
            "09458.16723",
            "09458.16723"
        ],
        "Processed": [
            "09458.16723",
            "09458.16723",
            "09458.16723",
            "09458.16723",
            "09458.16723",
            "09458.16723",
            "09458.16723",
            "09458.16723",
            "09458.16723",
            "09458.16723",
            "09458.16723",
            "09458.16723",
            "09458.16723",
            "09458.16723",
            "09458.16723",
            "09458.16723",
            "09458.16723",
            "09458.16723",
            "09458.16723",
            "09458.16723",
            "09458.16723",
            "09458.16723",
            "09458.16723",
            "09458.16723",
            "09458.16723",
            "09458.16723",
            "09458.16723",
            "09458.16723",
            "09458.16723",
            "09458.16723"
        ]
    },
    "Medium": {
        "Unprocessed": [
            "8658910724",
            "8658010724",
            "8653910724",
            "865.3910724",
            "865.3910724",
            "865.3910724",
            "865.3910724",
            "865.3910724",
            "865.3010724",
            "865.3010724",
            "865.3910724",
            "865.3010724",
            "865.3910724",
            "865.3910724",
            "8658910724",
            "865.3910724",
            "865.3010724",
            "8653910724",
            "865.3910724",
            "865.3010724",
            "865.3910724",
            "8653910724",
            "865.3910724",
            "865.3910724",
            "865.3910724",
            "865.3010724",
            "865.3910724",
            "865.8910724",
            "8658910724",
            "865.8910724"
        ],
        "Processed": [
            "865801072",
            "865.3910724",
            "8658010724",
            "8653910724",
            "8658010724",
            "8658910724",
            "8658010724",
            "865801072",
            "8658010724",
            "8658010724",
            "8658010724",
            "8653910724",
            "8658010724",
            "8658010724",
            "865801072",
            "8653910724",
            "8653910724",
            "8653910724",
            "8653910724",
            "8658010724",
            "865801072",
            "8658910724",
            "8653910724",
            "865801072",
            "8658010724",
            "8658010724",
            "8658010724",
            "8658010724",
            "86580102",
            "865.3910724"
        ]
    },
    "Small": {
        "Unprocessed": [
            "082307154",
            "0802807154",
            "08287154",
            "082867154",
            "0",
            "08928671544",
            "08280754",
            "08207154",
            "05",
            "0",
            "08280754",
            "02367154",
            "0",
            "080230754",
            "0892867154",
            "0",
            "0802807154",
            "028754",
            "082807154",
            "05",
            "082867154",
            "082307154",
            "02867154",
            "082867154",
            "082867154",
            "082867154",
            "02807154",
            "08280754",
            "082307154",
            "0802867154"
        ],
        "Processed": [
            "0275",
            "026715",
            "08280715",
            "00280715",
            "025",
            "0825",
            "08280715",
            "025",
            "0026715",
            "08275",
            "02",
            "0820715",
            "4",
            "0802875",
            "0828075",
            "8826715",
            "08029075+",
            "0828075",
            "025",
            "0821715",
            "0828075+",
            "0820715",
            "089230715",
            "025",
            "0402807157",
            "082675",
            "08275",
            "0828715",
            "0828715",
            "080286715"
        ]
    }
},
{
    "Image code": "12",
    "Big": {
        "Unprocessed": [
            "2",
            "1",
            "2",
            "",
            "",
            "",
            "2",
            "2",
            "8",
            "2",
            "2",
            "",
            "2",
            "",
            "2",
            "2",
            "",
            "8",
            "2",
            "3",
            "5",
            "28",
            "",
            "2",
            "2",
            "",
            "28",
            "3",
            "",
            "5"
        ],
        "Processed": [
            "239+178650",
            "2394178650",
            "2394178650",
            "2394178650",
            "2894178650",
            "289+178650",
            "2394178650",
            "2894178650",
            "2394178650",
            "2394178650",
            "2394178650",
            "2394178650",
            "2894178650",
            "2394178650",
            "2394178650",
            "2394178650",
            "239.178650",
            "2394178650",
            "2394178650",
            "2394178650",
            "2394178650",
            "23944178650",
            "2394178650",
            "2394178650",
            "2394178650",
            "2394178650",
            "2394178650",
            "2394178650",
            "2394178650",
            "239+178650"
        ]
    },
    "Medium": {
        "Unprocessed": [
            "2",
            "2",
            "1",
            "",
            "2",
            "",
            "3",
            "5",
            "3",
            "5",
            "2",
            "",
            "2",
            "5",
            "2",
            "3",
            "",
            "",
            "2",
            "2",
            "5",
            "2",
            "",
            "",
            "3",
            "2",
            "2",
            "",
            "5",
            ""
        ],
        "Processed": [
            "9",
            "408",
            "06",
            "30",
            "98",
            "38",
            "70",
            "3888",
            "208",
            "28",
            "008",
            "908",
            "2046",
            "90",
            "38",
            "3",
            "288",
            "008",
            "00",
            "0078",
            "0",
            "907",
            "30",
            "356",
            "3",
            "00",
            "3",
            "44084",
            "4086",
            "980"
        ]
    },
    "Small": {
        "Unprocessed": [
            "",
            "2",
            "5",
            "1",
            "1",
            "2",
            "5",
            "",
            "5",
            "",
            "1",
            "5",
            "1",
            "5",
            "2",
            "5",
            "2",
            "5",
            "2",
            "",
            "2",
            "5",
            "2",
            "5",
            "1",
            "2",
            "3",
            "2",
            "",
            "2"
        ],
        "Processed": [
            "48",
            "4",
            "4",
            "4",
            "3",
            "4",
            "3",
            "4",
            "8",
            "3",
            "3",
            "4",
            "3",
            "4",
            "3",
            "3",
            "4",
            "4",
            "4",
            "3",
            "4",
            "4",
            "4",
            "3",
            "3",
            "4",
            "4",
            "3",
            "4",
            "3"
        ]
    }
},
{
    "Image code": "13",
    "Big": {
        "Unprocessed": [
            "09.84531672",
            "09.84531672",
            "09.84531672",
            "09.84531672",
            "09.84531672",
            "09.84531672",
            "09.84531672",
            "09.84531672",
            "09.84531672",
            "09.84531672",
            "09.84531672",
            "09.84531672",
            "09.84531672",
            "09.84531672",
            "09.84531672",
            "09.84531672",
            "09.84531672",
            "09.84531672",
            "09.84531672",
            "09.84531672",
            "09.84531672",
            "09.84531672",
            "09.84531672",
            "09.84531672",
            "09.84531672",
            "09.84531672",
            "09.84531672",
            "09.84531672",
            "09.84531672",
            "09.84531672"
        ],
        "Processed": [
            "09.84531672",
            "09.84531672",
            "09.84531672",
            "09.84531672",
            "09.84531672",
            "09.84531672",
            "09.84531672",
            "09.84531672",
            "09.84531672",
            "09.84531672",
            "09.84531672",
            "09.84531672",
            "09.84531672",
            "09.84531672",
            "09.84531672",
            "09.84531672",
            "09.84531672",
            "09.84531672",
            "09.84531672",
            "09.84531672",
            "09.84531672",
            "09.84531672",
            "09.84531672",
            "09.84531672",
            "09.84531672",
            "09.84531672",
            "09.84531672",
            "09.84531672",
            "09.84531672",
            "09.84531672"
        ]
    },
    "Medium": {
        "Unprocessed": [
            "612.8439750",
            "6128439750",
            "612.8439750",
            "612.8439750",
            "612.8439750",
            "672.8439750",
            "612.8439750",
            "612.8439750",
            "612.8439750",
            "612.8439750",
            "612.8439750",
            "672.8439750",
            "612.8439750",
            "612.8439750",
            "612.8439750",
            "612.8439750",
            "612.8439750",
            "612.8439750",
            "6128439750",
            "612.8439750",
            "6128439750",
            "612.8439750",
            "612.8489750",
            "6128439750",
            "6128439750",
            "612.8439750",
            "612.8439750",
            "612.8439750",
            "612.8439750",
            "612.8439750"
        ],
        "Processed": [
            "612.8+39750",
            "612.8439750",
            "612.8439750",
            "612.8439750",
            "612.8439750",
            "612.8439750",
            "612.8439750",
            "612.8439750",
            "612.8439750",
            "612.8439750",
            "612.8439750",
            "612.8439750",
            "612.8439750",
            "612.8439750",
            "612.8439750",
            "612.8439750",
            "612.8439750",
            "612.84+39750",
            "612.8439750",
            "612.8439750",
            "612.84+39750",
            "612.8439750",
            "612.8489750",
            "612.8439750",
            "612.8439750",
            "612.8439750",
            "612.8439750",
            "612.8439750",
            "612.84+39750",
            "612.8439750"
        ]
    },
    "Small": {
        "Unprocessed": [
            "688",
            "3816",
            "886",
            "8",
            "08620",
            "381620",
            "37862",
            "58",
            "58",
            "01620",
            "08",
            "5868",
            "681620",
            "3781620",
            "5",
            "58",
            "07810",
            "91",
            "98",
            "88",
            "0781620",
            "886",
            "886",
            "37860",
            "380",
            "486",
            "0860",
            "3816",
            "3860",
            "8781620"
        ],
        "Processed": [
            "886",
            "38620",
            "6862",
            "582",
            "36",
            "6816",
            "586290",
            "58",
            "5862",
            "612",
            "68",
            "686",
            "578620",
            "58162",
            "582",
            "56",
            "382",
            "386",
            "386",
            "98",
            "0816",
            "886",
            "8162",
            "6",
            "38",
            "986",
            "8862",
            "36",
            "9",
            "816"
        ]
    }
},
{
    "Image code": "20",
    "Big": {
        "Unprocessed": [
            "789325046.1",
            "789325046.1",
            "789325046.1",
            "789325046.1",
            "789325046.1",
            "789325046.1",
            "789325046.1",
            "789325046.1",
            "789325046.1",
            "789325046.1",
            "789325046.1",
            "789325046.1",
            "789325046.1",
            "789325046.1",
            "789325046.1",
            "789325046.1",
            "789325046.1",
            "789325046.1",
            "789325046.1",
            "789325046.1",
            "789325046.1",
            "789325046.1",
            "789325046.1",
            "789325046.1",
            "789325046.1",
            "789325046.1",
            "789325046.1",
            "789325046.1",
            "789325046.1",
            "789325046.1"
        ],
        "Processed": [
            "7893250461",
            "7893250461",
            "7893250461",
            "7893250461",
            "7893250461",
            "789325046.1",
            "7893250461",
            "7393250461",
            "7893250461",
            "7893250461",
            "7893250461",
            "7393250461",
            "789325046.1",
            "7893250461",
            "7893250461",
            "7893250461",
            "7893250461",
            "7893250461",
            "7893250461",
            "7393250461",
            "7893250461",
            "7893250461",
            "7893250461",
            "7893250461",
            "7893250461",
            "7893250461",
            "7893250461",
            "7893250461",
            "7893250461",
            "7893250461"
        ]
    },
    "Medium": {
        "Unprocessed": [
            "8539746210",
            "8539746210",
            "8539746210",
            "8539746210",
            "8539746210",
            "8539746210",
            "8539746210",
            "85397.46210",
            "5539746210",
            "8539746210",
            "8539746210",
            "8539746210",
            "8539746210",
            "8539746210",
            "8539746210",
            "5539746210",
            "8539746210",
            "8539746210",
            "8539746210",
            "8539746210",
            "8539746210",
            "85397.46210",
            "85397.46210",
            "8539746210",
            "85397.46210",
            "8539746210",
            "8539746210",
            "8539746210",
            "8539746210",
            "85397.46210"
        ],
        "Processed": [
            "858974670",
            "6539746210",
            "5539746210",
            "8589746210",
            "85897.46210",
            "858974610",
            "858974610",
            "83.9746210",
            "653974010",
            "8539746210",
            "85397.46710",
            "8589746210",
            "5589746210",
            "8589746210",
            "5589746210",
            "8589740710",
            "6589746210",
            "8589746210",
            "8589748210",
            "858974610",
            "8539746210",
            "5589746210",
            "8589746210",
            "8539746210",
            "85974610",
            "8589746210",
            "558974010",
            "6539746210",
            "558974810",
            "8589746210"
        ]
    },
    "Small": {
        "Unprocessed": [
            "6102.843957",
            "6102843957",
            "6102843957",
            "6102.843957",
            "688",
            "610887",
            "6102.843957",
            "6108",
            "6102.843957",
            "61028+3957",
            "6102.843957",
            "6102.843857",
            "6102.843957",
            "8102843957",
            "6102.843957",
            "6102.843957",
            "6102.843957",
            "6102.843957",
            "6102.843957",
            "8102.843957",
            "6102.843957",
            "6188",
            "6102.843957",
            "6085",
            "6102.843957",
            "68",
            "0087",
            "60457",
            "6102.843957",
            "6108"
        ],
        "Processed": [
            "6108450",
            "6428",
            "81856",
            "610284584",
            "0",
            "618",
            "61828188582",
            "65",
            "6101243857-",
            "61157",
            "51044",
            "5028457-",
            "6102.841854-",
            "61285",
            "6107244857",
            "0257",
            "018",
            "8182857",
            "618157",
            "61828485-",
            "824",
            "6",
            "812457-",
            "61+",
            "0",
            "0",
            "084",
            "61815",
            "6102847",
            "618"
        ]
    }
},
{
    "Image code": "21",
    "Big": {
        "Unprocessed": [
            "8942.871605",
            "8942.871605",
            "3942.871605",
            "5942.871605",
            "8942.871605",
            "3942.871605",
            "3942.871605",
            "3942.871605",
            "3942.871605",
            "3942.871605",
            "3942.871605",
            "8942.871605",
            "3942.871605",
            "8942.871605",
            "3942.871605",
            "3942.871605",
            "3942.871605",
            "8942.871605",
            "5942.871605",
            "8942.871605",
            "8942.871605",
            "3942.871605",
            "5942.871605",
            "8942.871605",
            "3942.871605",
            "5942.871605",
            "3942.871605",
            "8942.871605",
            "8942.871605",
            "5942.871605"
        ],
        "Processed": [
            "8942.871605",
            "8942.871605",
            "8942.871605",
            "8942.871605",
            "8942871605",
            "8942.871605",
            "8942.871605",
            "8942.871605",
            "3942.871605",
            "8942.871605",
            "3942.871605",
            "8942.871605",
            "8942.871605",
            "8942.871605",
            "8942.871605",
            "3942.871605",
            "3942871605",
            "8942.871605",
            "5942.871605",
            "8942.871605",
            "8942871605",
            "8942.871605",
            "8942.871605",
            "3942.871605",
            "3942.871605",
            "8942.871605",
            "8942.871605",
            "8942.871605",
            "8942.871605",
            "3942.871605"
        ]
    },
    "Medium": {
        "Unprocessed": [
            "9478630251",
            "9478630251",
            "94+78630251",
            "9786302.51",
            "9478630251",
            "9478630251",
            "94786302.51",
            "94+78630251",
            "9478630251",
            "9478630251",
            "9478630251",
            "9478630251",
            "94786302.51",
            "9478630251",
            "8478680251",
            "9478630251",
            "94786302.51",
            "9478630251",
            "9478630251",
            "9478630251",
            "9478630251",
            "9478630251",
            "978630251",
            "9478630251",
            "9478630251",
            "9478630251",
            "9478630251",
            "9478630251",
            "9478630251",
            "9478630251"
        ],
        "Processed": [
            "378630251",
            "9478630251",
            "3778630251",
            "378630251",
            "9478630251",
            "9478630251",
            "9478630251",
            "978630251",
            "9478630251",
            "978630251",
            "478630251",
            "378630251",
            "9478630251",
            "478630251",
            "9478630251",
            "478630251",
            "978630251",
            "9778630251",
            "9778630251",
            "9478630251",
            "9478630251",
            "9478630251",
            "978630251",
            "9778630251",
            "9478630251",
            "9478630251",
            "978630251",
            "9478630251",
            "9478630251",
            "478630251"
        ]
    },
    "Small": {
        "Unprocessed": [
            "35203018",
            "3.4318",
            "752408",
            "35",
            "35",
            "203018",
            "75.430",
            "703018",
            "359203078",
            "75.48",
            "350",
            "752031",
            "7.4078",
            "75203078",
            "3520",
            "35",
            "75203018",
            "35",
            "75920808",
            "35",
            "35",
            "35020308",
            "7508018",
            "7+0",
            "35",
            "3548",
            "35",
            "3",
            "30",
            "35"
        ],
        "Processed": [
            "350",
            "7.8",
            "728",
            "3006",
            "3.8",
            "70",
            "3",
            "3",
            "3",
            "48",
            "3",
            "3",
            "79208",
            "4.",
            "3",
            "3",
            "78",
            "79",
            "708",
            "4",
            "38",
            "30",
            "70",
            "3",
            "48",
            "72",
            "750",
            "30",
            "3.",
            "78"
        ]
    }
},
{
    "Image code": "22",
    "Big": {
        "Unprocessed": [
            "5",
            "5",
            "",
            "",
            "2",
            "22",
            "",
            "1",
            "1",
            "2",
            "",
            "3",
            "2",
            "1",
            "2",
            "",
            "",
            "28",
            "22",
            "",
            "2",
            "8",
            "2",
            "2",
            "5",
            "5",
            "",
            "",
            "",
            ""
        ],
        "Processed": [
            "5518205749",
            "5618208749",
            "56182037+9",
            "5518208749",
            "56182037+2",
            "5618205749",
            "5618208749",
            "561820374.9",
            "5615205749",
            "561820374.9",
            "561820374.9",
            "56182037+9",
            "5618203749",
            "5515205749",
            "5618203749",
            "561820574.9",
            "5618208749",
            "5618203749",
            "5618205749",
            "561820574.9",
            "561820374.9",
            "561820374.9",
            "56182037+9",
            "5615205749",
            "5618205749",
            "5618203749",
            "5618208749",
            "5618205749",
            "5518205749",
            "5618203749"
        ]
    },
    "Medium": {
        "Unprocessed": [
            "",
            "",
            "2",
            "28",
            "5",
            "28",
            "2",
            "",
            "",
            "1",
            "3",
            "",
            "5",
            "2",
            "28",
            "",
            "5",
            "28",
            "2",
            "",
            "",
            "3",
            "2",
            "",
            "",
            "1",
            "2",
            "",
            "",
            ""
        ],
        "Processed": [
            "30",
            "48",
            "3849",
            "3897",
            "39",
            "3490",
            "8895",
            "349",
            "3",
            "898",
            "89",
            "30",
            "37",
            "34.",
            "4898",
            "3490",
            "8850",
            "349",
            "39",
            "349.",
            "89",
            "3",
            "38",
            "349",
            "31",
            "39",
            "389",
            "3",
            "39",
            "49"
        ]
    },
    "Small": {
        "Unprocessed": [
            "2",
            "1",
            "2",
            "3",
            "",
            "",
            "",
            "",
            "1",
            "1",
            "5",
            "2",
            "2",
            "2",
            "3",
            "",
            "",
            "",
            "3",
            "",
            "3",
            "1",
            "2",
            "",
            "2",
            "",
            "",
            "1",
            "2",
            ""
        ],
        "Processed": [
            "4",
            "3",
            "3",
            "4",
            "3",
            "4",
            "3",
            "3",
            "3",
            "4",
            "3",
            "4",
            "4",
            "3",
            "3",
            "3",
            "8",
            "3",
            "3",
            "4",
            "4",
            "4",
            "3",
            "3",
            "48",
            "4",
            "4",
            "4",
            "4",
            "4"
        ]
    }
},
{
    "Image code": "23",
    "Big": {
        "Unprocessed": [
            "37.40268519",
            "37.40268519",
            "37.40268519",
            "37.40268519",
            "37.40268519",
            "37.40268519",
            "37.0268519",
            "37.40268519",
            "37.40268519",
            "37.40268519",
            "37.40268519",
            "37.40268519",
            "37.40268519",
            "37.40268519",
            "37.40268519",
            "3740268519",
            "3740268519",
            "37.0268519",
            "37.0268519",
            "37.0268519",
            "3740268519",
            "37.40268519",
            "37.40268519",
            "37.40268519",
            "37.40268519",
            "3740268519",
            "3740268519",
            "37.40268519",
            "37.0268519",
            "37.40268519"
        ],
        "Processed": [
            "37.40268519",
            "37..0268519",
            "37.40268519",
            "3740268519",
            "37.40268519",
            "37.40268519",
            "37.40268519",
            "37.40268519",
            "37..40268519",
            "37.40268519",
            "37.40268519",
            "37.40268519",
            "37.40268519",
            "37.40268519",
            "37.40268519",
            "37.40268519",
            "37.40268519",
            "37.40268519",
            "37.40268519",
            "37.40268519",
            "37.40268519",
            "37.40268519",
            "37.40268519",
            "37.40268519",
            "37.40268519",
            "37.40268519",
            "37.40268519",
            "37.40268519",
            "37.40268519",
            "37.40268519"
        ]
    },
    "Medium": {
        "Unprocessed": [
            "741895.6203",
            "741895.6203",
            "741895.6203",
            "71595.6203",
            "747895.6203",
            "77895.6203",
            "747895.6203",
            "747895.6203",
            "77895.6203",
            "7+7895.6203",
            "74895.6203",
            "747895.6203",
            "71895.6203",
            "747895.6203",
            "741895.6203",
            "741895.6203",
            "747895.6203",
            "74895.6203",
            "747895.6203",
            "747895.6203",
            "747895.6203",
            "747895.6203",
            "741895.6203",
            "741895.6203",
            "741895.6203",
            "7895.6203",
            "741895.6203",
            "747895.6203",
            "77895.6203",
            "747895.6203"
        ],
        "Processed": [
            "741895.6203",
            "715956203",
            "718956203",
            "715956203",
            "71895.6203",
            "715956203",
            "741595.6203",
            "7418956203",
            "715956203",
            "775956203",
            "718956203",
            "741956203",
            "71895.6203",
            "741595.6203",
            "741895.6203",
            "747895.6203",
            "741956203",
            "71895.6203",
            "715956203",
            "7418956203",
            "718956203",
            "71595.6203",
            "71895.6203",
            "71895.6203",
            "718956203",
            "741895.6203",
            "741895.6203",
            "741895.6203",
            "71835.6203",
            "741895.6203"
        ]
    },
    "Small": {
        "Unprocessed": [
            "361",
            "8882",
            "869+1",
            "371",
            "371",
            "88",
            "87701",
            "37671",
            "88+01",
            "3671",
            "8788",
            "3701",
            "3601",
            "88844",
            "88",
            "36",
            "36+1",
            "38",
            "8+1",
            "31",
            "3-41",
            "8+1",
            "8741",
            "888",
            "880",
            "36",
            "8787",
            "3+41",
            "8848",
            "888"
        ],
        "Processed": [
            "661",
            "3801",
            "8641",
            "68",
            "47",
            "8630",
            "360",
            "36834",
            "8820",
            "36301",
            "660",
            "3",
            "360",
            "6601",
            "8201",
            "3601",
            "86+01",
            "30",
            "6+",
            "81",
            "8621",
            "887",
            "676401",
            "3",
            "8",
            "68+01",
            "86+1",
            "36",
            "860",
            "688"
        ]
    }
},
{
    "Image code": "40",
    "Big": {
        "Unprocessed": [
            "256222.32332",
            "25622232332",
            "256222.3333",
            "256222333",
            "256272233",
            "8568724932",
            "",
            "2562724333",
            ".5502433",
            "",
            "85632222333",
            "",
            "856872.4932",
            "856272233",
            "856072.4932",
            "85527232332",
            "256272233",
            "",
            "",
            "856872.4933",
            "856322233.",
            "",
            "",
            "8568724932",
            "856072.4933",
            "856072.4931",
            "8560724.4932",
            "2562723233",
            "856072.4936",
            "25622223332"
        ],
        "Processed": [
            "856072.4931",
            "856072.4931",
            "856872.4933",
            "856072.4931",
            "856072.4931",
            "856072.493.-..",
            "856072.4933",
            "856072-4932",
            "856072.4931",
            "856072.4931.",
            "856072.4931",
            "856072.4932",
            "856072.4931",
            "856072.4331",
            "856072.4931",
            "856072.4931",
            "856072.4931",
            "856072.4931",
            "856072.4931",
            "856072.4931",
            "856072.4931",
            "856072.4931",
            "856072.4931",
            "856072.4931.",
            "856072.4931",
            "85607244931",
            "85607274931",
            "856072.4931",
            "856872.4932",
            "856072.4932"
        ]
    },
    "Medium": {
        "Unprocessed": [
            "325233524",
            "",
            "0256594671",
            "32521-63332",
            "292223",
            "225635327",
            "",
            "225233322-2",
            "",
            "",
            "2293352223",
            "0258354675",
            "23273332272",
            "",
            "",
            "",
            "3.52323352673",
            "2253335257",
            "2253333265",
            "",
            "0258334676",
            "",
            "",
            "",
            "",
            "",
            "",
            "6352395672",
            "6253232579",
            "5256333.6-"
        ],
        "Processed": [
            "0258394.672",
            "8258334671",
            "0252394.673",
            "2.256354671",
            "0256394.671",
            "0258354671",
            "029359571",
            "0258396571",
            "029334.671",
            "0293946711",
            "8258394.671",
            "1-258394671",
            "0258394671",
            "6258.394671",
            "-19258394671",
            "0258394671",
            "0256394-.671",
            "2258354673",
            "0258354671",
            "2-256394.673",
            "0256394671",
            "2-258394.671",
            "0258334672",
            "858395671",
            "6258394671",
            "625684673",
            "0-258354671",
            "0258395675",
            "0258294671",
            "1.89334671"
        ]
    },
    "Small": {
        "Unprocessed": [
            "",
            "",
            "",
            "",
            "",
            "",
            "",
            "",
            "",
            "",
            "",
            "",
            "532.23.21-215.2267521712533.2353",
            "",
            "",
            "",
            "",
            "",
            "",
            "",
            "",
            "",
            "5-7-525975.22725..5257535",
            "",
            "",
            "",
            "",
            "",
            "",
            ""
        ],
        "Processed": [
            "...59424-..-75.7.3-",
            "......-.2.....5.-.3-.22..5..",
            "",
            "",
            "..36....0.7.5-2998..5-2.-........-2",
            "",
            "..2....1.652....",
            "2..--.7..1.............61....5.....671..",
            "",
            "",
            "72.5.67.7--.-..-.",
            "6-.0985-",
            ".5..3..5..92.-8-2...-9..0.-......542",
            "",
            "2.0-57-.-........",
            "-539951.",
            "........-.9.7-.",
            "-.-692663",
            "",
            "........--35",
            "6676823.-2",
            "",
            ".5...5.7....5-.-...-..-53.5-2.",
            "",
            "460598..71..2",
            "..5.6.9522683.....915-....222",
            "",
            ".0.....8..03..6.3......-.....",
            "",
            "5.559386..5--337-."
        ]
    }
},
{
    "Image code": "41",
    "Big": {
        "Unprocessed": [
            "",
            "722233332",
            "7.227222353322",
            ".7-233333332",
            "723233322",
            "76.5232335332",
            "",
            "7.232222354332",
            "752235322",
            "7-5325233332",
            "7.2222353222",
            "2.2.22222333322",
            "7.3222333322",
            "723332235322",
            "-22232333632",
            "7.680135942",
            "722232322",
            "7222353222",
            "",
            "722322333322",
            "7.680135342",
            "7.680135942",
            "722233222",
            "766235322",
            "",
            "722232322",
            "7632232322",
            "7.630135342",
            "25622235332",
            "-523235222"
        ],
        "Processed": [
            "7.680135942",
            "7.680135342",
            "7.680135942",
            "7.680135942",
            "7.680135942",
            "7.680135942",
            "7.680135942",
            "7.680135942",
            "7.680135942",
            "7.680135942",
            "7.680135942",
            "7.680135942",
            "7-680135942",
            "7.680135942",
            "7.680135942",
            "7.680135942",
            "7.680135942",
            "7.620135942",
            "7.680135942",
            "7.680135942",
            "756610135942",
            "7.680135542",
            "7.680135942",
            "7.680135942",
            "7.680135942",
            "7.680135942",
            "7.680135942",
            "7.680135942",
            "7.680135942",
            "7.660135942"
        ]
    },
    "Medium": {
        "Unprocessed": [
            "5.3422623+3",
            "3.37232433",
            "33722233+3",
            "5.3522+543.2",
            "33.23243.2",
            "",
            "",
            "534222332",
            "33223333",
            "337.22543-2",
            "5.34225623",
            "332255525",
            "5.372-126432",
            "53.22126436",
            "5370126432",
            "33722223",
            "5.370125436",
            "",
            "5370126432",
            "5.34226-23+3",
            "537012646.68",
            "2372233232",
            "",
            "",
            "5432+-32262.232",
            "3372253165",
            "13926333",
            "",
            "537+312641+9",
            "362273322252.33"
        ],
        "Processed": [
            "3970126436",
            "5-973126436",
            "5.370126436",
            "5.37012-5436",
            "5.37-1.7126438",
            "5.370126438",
            "5.370126418",
            "5.37012-5432",
            "5.370125435",
            "5..37012643-3",
            "5.3-10126438",
            "5.370126432-",
            "5.270126438",
            "5.34131264364",
            "5.37212643-9",
            "5.3761-..1-424.32",
            "-537012642-9",
            "5.37012643-2",
            "5.5753126432",
            "5-340162.45261",
            "5.372126438",
            "5.3713126433",
            "5572126438",
            "5.3721226438",
            "5.370126432",
            "5.370126438",
            "5.3521126432",
            "5.370126432",
            "543761126438",
            "5.5701264342"
        ]
    },
    "Small": {
        "Unprocessed": [
            ".373356245",
            "612+2273",
            "6423.42275",
            "5++2724462",
            "642512255",
            "4+52+",
            "",
            "",
            "",
            "229.42137.6",
            "2029423795",
            "",
            "2+6424977726",
            "22332262",
            "6.-223223.3",
            "22-+.362242",
            "",
            "225273335723",
            "",
            "",
            "",
            "523.383333",
            "6.3733325035",
            "2-2517263735",
            "2534552525",
            "",
            "245352662",
            "623324-3",
            "6373422735",
            "22.-37+2333"
        ],
        "Processed": [
            "2394-29795",
            "66.441-422-755",
            "2123459795",
            "5+62-1-35",
            "6739.4293.95",
            "5539439725",
            "5994543735",
            "503942-3735",
            "68242423735",
            "2.841213785",
            "5543423755",
            "2-543.4213735",
            "6-594273736",
            "283.4229735",
            "55-3.43295",
            "59+-92635",
            "523251221535",
            "623429795",
            "6.594221735",
            "-1-.135582735",
            "5-556429735",
            "5.-2542.3-65",
            "63.-799723",
            "2+5942-2722",
            "6-53.45.2435",
            "5-594213735",
            "2-5942-2735",
            "6.5-3-42-2-35",
            "6-723.658755",
            "515942-0.-35-"
        ]
    }
},
{
    "Image code": "42",
    "Big": {
        "Unprocessed": [
            "292663",
            "3282.6453",
            "329276453",
            "",
            "",
            "",
            "",
            "",
            "892-6453",
            "",
            "",
            "",
            "",
            "",
            "692663",
            "21-58.276453",
            "",
            "8192764537",
            "2926453",
            "29.276453",
            "219236453",
            "22926453",
            "2192.6453",
            "",
            "2209263253",
            "",
            "",
            "",
            "",
            "319-.26453"
        ],
        "Processed": [
            "019276453",
            "0192-6453",
            "0129276453",
            "019.276453",
            "09926453",
            "0192.6453",
            "0192.6453",
            "09276453",
            "01926453",
            "019246453",
            "01926463",
            "0198276453",
            "019276453",
            "019276453",
            "01926463",
            "019.276453",
            "0192663",
            "..49276453",
            "01926453",
            "019.26453",
            "01926463",
            "0192.6453",
            "019.2.6453",
            "019276453",
            "019276453",
            "019.26453",
            "019.26453",
            "01926.63",
            "019.2.6453",
            "019.26453"
        ]
    },
    "Medium": {
        "Unprocessed": [
            "",
            "",
            "",
            "",
            "",
            "2725.52677224",
            "",
            "",
            "63325308",
            "",
            "",
            "",
            "7-233732228",
            "",
            "",
            "",
            "793322.2219",
            "",
            "3-933425+4350",
            "733.553238",
            "23533++24328.0-.31",
            "",
            "3252222548",
            "73-5.232268",
            "",
            "",
            "",
            "",
            "",
            ""
        ],
        "Processed": [
            "73192395",
            "70-2.86",
            "7592.37105",
            "73512329.5",
            "75621246",
            "7.020465",
            "702.0496",
            "76512124.6",
            "7662.08",
            "74.052.096",
            "75020..6",
            "3352.005",
            "782325",
            "7692.0405",
            "7.792.0.95",
            "75621195",
            "78923295",
            "8-552.5305",
            "782.096",
            "7.592.095",
            "71352.646",
            "75362.0885",
            "7602.0496",
            "5652.096",
            "7352115",
            "7352.095",
            "7.682.096",
            "7.3662096",
            "76821295",
            "71.5512.06"
        ]
    },
    "Small": {
        "Unprocessed": [
            "",
            "",
            "8-544.-6..1.",
            "",
            "",
            "",
            "",
            "",
            "",
            "",
            "",
            "",
            "",
            "",
            "",
            "",
            "",
            "746.8.46..-.",
            "..1-74..5444745.3",
            "",
            "",
            "",
            "",
            "",
            "",
            "",
            "..44-2-572.27..2",
            "",
            "",
            ""
        ],
        "Processed": [
            "675689",
            "76-29-9487",
            "",
            "65232921",
            "826.9",
            "8310",
            "35213..4",
            "6692970",
            "672309",
            "09903564",
            "",
            "382909",
            "9-23.9",
            "389-9",
            "69809",
            "3850",
            "700709",
            "8540575",
            "49-065",
            "",
            "",
            "853021",
            "709180",
            "65389.",
            "52580",
            "--4",
            "",
            "..",
            "883.99",
            "929.09"
        ]
    }
},
{
    "Image code": "43",
    "Big": {
        "Unprocessed": [
            "34335627.80",
            "74060782",
            "+122.70792",
            "2+126274.20",
            "4-2962723",
            "-74335627.32",
            "42..0-82",
            "",
            "26-33627.82",
            "+2.52732",
            "97.-2265.367.825",
            "-44262-92",
            "2443627.80",
            "41-702780",
            "6-12707.80",
            "3455262760",
            "-7742627.90",
            "34535627-80",
            "31455.5627.23",
            "24-3639627.20",
            "343932627.22",
            "3433627332",
            "-4062782",
            "345221627730",
            "342232627...20",
            "334331627-80",
            "4443627.20",
            "35532627.80",
            "34535627.80",
            "3425627.827"
        ],
        "Processed": [
            "34591627.80",
            "34591627.80",
            "34591627.80",
            "34591627.80",
            "34591627.80",
            "34591627.80",
            "34591627.80",
            "34591627.80",
            "34591627.80",
            "34591627.80",
            "34591627.80",
            "34591627.80",
            "34591627.80",
            "34591627.80",
            "34591627.80",
            "34591627.80",
            "34591627.80",
            "34591627.80",
            "34591627.80",
            "34591627.80",
            "34591627.80",
            "34591627.80",
            "34591627.80",
            "34591627.80",
            "34591627.80",
            "34591627.80",
            "34591627.80",
            "34591627.80",
            "34591627.80",
            "34591627.80"
        ]
    },
    "Medium": {
        "Unprocessed": [
            "5-+2.233+5275.3",
            "62.36.363754",
            "--35.36575-6",
            ".-2255.375.2",
            "922..53351754",
            "74.2.56363754",
            "3.333153254",
            "1253.53754.",
            "+2-31313637535",
            "155.763233754",
            "1203563754",
            "",
            "-263363254",
            "+2.365754",
            "923.55342173757",
            "+25365754",
            "22.55363724",
            "92....-63.557547",
            "3-2253557352",
            "+3..73555.64",
            "+22-51359734",
            "-22-5525754",
            "2523...3-254",
            "122.3545..37454",
            "+206555754",
            "1.-5233537544",
            "12.2523652754",
            "3353754",
            ".2.26325.754",
            "142211-754"
        ],
        "Processed": [
            "12.06369754",
            "12.06369754",
            "12.08369754",
            "12.06369754",
            "12.0-8369754",
            "12.08369754",
            "12.08369754",
            "12.18369754",
            "12.08369754",
            "12.08369754",
            "12.08369754",
            "12.08369754",
            "12.08369754",
            "12.02369754",
            "12.08369754",
            "12.8369754",
            "12.08369754",
            "12.0.959754",
            "12.08369754",
            "12.08369754",
            "12.08369754",
            "12.06369754",
            "12.08369754",
            "12.06369754",
            "12.08369754",
            "12.0859754",
            "12.08369754",
            "12.08369754",
            "12.28369754",
            "12.08369754"
        ]
    },
    "Small": {
        "Unprocessed": [
            ".22...55.26267",
            "55-165.3.77",
            "22.434232274",
            "5.44234.7.7",
            "3.343365.337-",
            "5.-.2127524747",
            "44-8.4",
            "6.+..02-.",
            "52..3642",
            "57365391+227.",
            "-51+23-8.2",
            "547537.5-2.5",
            "1+-.4",
            "++.524",
            "451322422.1",
            "..1+1+12",
            "8114522.2",
            "..+24.22127",
            "2154.33755-27",
            "534452+5237",
            "11..0+7212",
            "5.143.776257",
            "114622+.132",
            "5336226217",
            "624357327.7",
            "554.55762+.7",
            "15.-+.6.5..1",
            "524527222",
            "-524426765119",
            "+2.54522.54.2"
        ],
        "Processed": [
            "89520.",
            "884.2935257",
            "86775267",
            "81359520",
            "93.93377",
            "8296267",
            "865620",
            "28820",
            "93.64.755257",
            "8656267",
            "8282520",
            "938695257",
            "8262620",
            "83.695267",
            "936-9620",
            "934682267",
            "8258620",
            "28693527",
            "8249628",
            "93.857257",
            "0345857257",
            "93582520",
            "83495267",
            "22.567267",
            "9358620",
            "9269620",
            "22.68520",
            "92592620",
            "93.63520",
            "33692520"
        ]
    }
}]